Workbook

Sheet A
B4: TP 10, 11 Y 12
B6: VALUACIÓN DE EMPRESAS - MODELO DCF
B9: Alumno | C9: Luca Camus
B10: Empresa | C10: Agrometal
B11: Ticker | C11: AGRO

Sheet Base
A4: Fecha | B4: MEP diario | D4: Fecha | E4: MEP | G4: Etiquetas de fila | H4: Promedio de MEP | K4: Fecha | L4: Merval | N4: Fecha | O4: Riesgo país | T4: IPC mensual base 2016 | U4: Inflación mensual | V4: Inflacion interanual | W4: Inflación promedio | Z4: Fecha | AA4: EMAE base 2004 s.e | AD4: Fecha | AE4: PBI cte a pesos 2004
A5: 45813 | B5: 1192.38 | D5: 45814 | E5: 1192.4 | G5: 2020 | H5: 122.63622 | K5: 45814 | L5: 2156778.5 | N5: 45814 | O5: 688 | S5: 43831 | T5: 289.8299 | V5: 0.529 | Z5: 43831 | AA5: 140.70852 | AD5: 43922 | AE5: 632389.35 | AH5: Etiquetas de fila | AI5: Promedio de PBI cte a pesos 2004
A6: 45812 | B6: 1193.22 | D6: 45813 | E6: 1192.38 | G6: 2021 | H6: 164.48068 | K6: 45813 | L6: 2124156 | N6: 45813 | O6: 688 | S6: 43862 | T6: 295.666 | U6: =T6/T5-1 -> 0.020136294 | V6: 0.503 | Z6: 43862 | AA6: 138.88807 | AD6: 44013 | AE6: 609379.99 | AH6: 2020 | AI6: 624591.29
A7: 45811 | B7: 1189.67 | D7: 45812 | E7: 1193.22 | G7: 2022 | H7: 250.58223 | K7: 45812 | L7: 2126915.2 | N7: 45812 | O7: 688 | S7: 43891 | T7: 305.5515 | U7: =T7/T6-1 -> 0.033434686 | V7: 0.484 | Z7: 43891 | AA7: 125.48317 | AD7: 44105 | AE7: 614192.48 | AH7: 2021 | AI7: 689809.93
A8: 45810 | B8: 1183.78 | D8: 45811 | E8: 1189.67 | G8: 2023 | H8: 573.54615 | K8: 45811 | L8: 2224638 | N8: 45811 | O8: 668 | S8: 43922 | T8: 310.1243 | U8: =T8/T7-1 -> 0.014965726 | V8: 0.456 | Z8: 43922 | AA8: 106.10837 | AD8: 44166 | AE8: 642403.32 | AH8: 2022 | AI8: 726162.09
A9: 45807 | B9: 1191.72 | D9: 45810 | E9: 1183.78 | G9: 2024 | H9: 1163.4084 | K9: 45810 | L9: 2206291.2 | N9: 45806 | O9: 663 | S9: 43952 | T9: 314.9087 | U9: =T9/T8-1 -> 0.015427363 | V9: 0.434 | Z9: 43952 | AA9: 117.63514 | AD9: 44287 | AE9: 652831.98 | AF9: =AE9/AE5-1 -> 0.032326008 | AH9: 2023 | AI9: 714463.6
A10: 45806 | B10: 1181.9 | D10: 45807 | E10: 1191.72 | G10: 2025 | H10: 1204.6832 | K10: 45807 | L10: 2278991.5 | N10: 45805 | O10: 655 | S10: 43983 | T10: 321.9738 | U10: =T10/T9-1 -> 0.022435392 | V10: 0.428 | Z10: 43983 | AA10: 124.84622 | AD10: 44378 | AE10: 723516.62 | AF10: =AE10/AE6-1 -> 0.18729961 | AH10: 2024 | AI10: 702181.22
A11: 45805 | B11: 1164.8 | D11: 45806 | E11: 1181.9 | G11: Total general | H11: 480.71848 | K11: 45806 | L11: 2308055.8 | N11: 45804 | O11: 666 | S11: 44013 | T11: 328.2014 | U11: =T11/T10-1 -> 0.019341946 | V11: 0.424 | Z11: 44013 | AA11: 126.19018 | AD11: 44470 | AE11: 686756.47 | AF11: =AE11/AE7-1 -> 0.11814536 | AH11: Total general | AI11: 691441.63
A12: 45804 | B12: 1161.3 | D12: 45805 | E12: 1164.8 | K12: 45805 | L12: 2344329.5 | N12: 45803 | O12: 666 | S12: 44044 | T12: 337.0632 | U12: =T12/T11-1 -> 0.027001104 | V12: 0.407 | Z12: 44044 | AA12: 129.01079 | AD12: 44531 | AE12: 696134.67 | AF12: =AE12/AE8-1 -> 0.083641139
A13: 45803 | B13: 1145.42 | D13: 45804 | E13: 1161.3 | K13: 45804 | L13: 2355098.2 | N13: 45800 | O13: 665 | S13: 44075 | T13: 346.6207 | U13: =T13/T12-1 -> 0.028355216 | V13: 0.366 | Z13: 44075 | AA13: 130.82176 | AD13: 44652 | AE13: 697592.04 | AF13: =AE13/AE9-1 -> 0.068562913
A14: 45800 | B14: 1143.32 | D14: 45803 | E14: 1145.42 | K14: 45803 | L14: 2370800 | N14: 45799 | O14: 665 | S14: 44105 | T14: 359.657 | U14: =T14/T13-1 -> 0.037609698 | V14: 0.372 | Z14: 44105 | AA14: 133.64962 | AD14: 44743 | AE14: 774238.21 | AF14: =AE14/AE10-1 -> 0.07010424 | AH14: 2020 | AI14: 624591.29 | AJ14: -0.099
A15: 45799 | B15: 1143.49 | D15: 45800 | E15: 1143.32 | K15: 45800 | L15: 2345902.2 | N15: 45798 | O15: 661 | S15: 44136 | T15: 371.0211 | U15: =T15/T14-1 -> 0.031597049 | V15: 0.358 | Z15: 44136 | AA15: 134.91069 | AD15: 44835 | AE15: 727933.42 | AF15: =AE15/AE11-1 -> 0.059958599 | AH15: 2021 | AI15: 689809.93 | AJ15: =AI15/AI14-1 -> 0.10441812
A16: 45798 | B16: 1148.8 | D16: 45799 | E16: 1143.49 | K16: 45799 | L16: 2314897 | N16: 45797 | O16: 663 | S16: 44166 | T16: 385.8826 | U16: =T16/T15-1 -> 0.040055673 | V16: 0.361 | Z16: 44166 | AA16: 136.76102 | AD16: 44896 | AE16: 704884.68 | AF16: =AE16/AE12-1 -> 0.012569426 | AH16: 2022 | AI16: 726162.09 | AJ16: =AI16/AI15-1 -> 0.052698797
A17: 45797 | B17: 1153.33 | D17: 45798 | E17: 1148.8 | K17: 45798 | L17: 2319548.5 | N17: 45796 | O17: 675 | S17: 44197 | T17: 401.5071 | U17: =T17/T16-1 -> 0.040490294 | V17: =T17/T5-1 -> 0.3853198 | Z17: 44197 | AA17: 139.73714 | AD17: 45017 | AE17: 705021.1 | AF17: =AE17/AE13-1 -> 0.010649574 | AH17: 2023 | AI17: 714463.6 | AJ17: =AI17/AI16-1 -> -0.016110016
A18: 45796 | B18: 1148.77 | D18: 45797 | E18: 1153.33 | K18: 45797 | L18: 2378464 | N18: 45793 | O18: 676 | S18: 44228 | T18: 415.8595 | U18: =T18/T17-1 -> 0.035746317 | V18: =T18/T6-1 -> 0.40651783 | Z18: 44228 | AA18: 137.25835 | AD18: 45108 | AE18: 733350.47 | AF18: =AE18/AE14-1 -> -0.052810274 | AH18: 2024 | AI18: 702181.22 | AJ18: =AI18/AI17-1 -> -0.017191052
A19: 45793 | B19: 1155.12 | D19: 45796 | E19: 1148.77 | K19: 45796 | L19: 2369505.2 | N19: 45792 | O19: 676 | S19: 44256 | T19: 435.8657 | U19: =T19/T18-1 -> 0.048108075 | V19: =T19/T7-1 -> 0.4264885 | Z19: 44256 | AA19: 140.61116 | AD19: 45200 | AE19: 723190.59 | AF19: =AE19/AE15-1 -> -0.006515474 | AH19: 2025 | AJ19: 0.055
A20: 45792 | B20: 1140.92 | D20: 45793 | E20: 1155.12 | K20: 45793 | L20: 2318360 | N20: 45791 | O20: 648 | S20: 44287 | T20: 453.6503 | U20: =T20/T19-1 -> 0.040802935 | V20: =T20/T8-1 -> 0.46280153 | Z20: 44287 | AA20: 139.63372 | AD20: 45261 | AE20: 696292.25 | AF20: =AE20/AE16-1 -> -0.012189834 | AH20: 2026 | AJ20: 0.045
A21: 45791 | B21: 1140.92 | D21: 45792 | E21: 1140.92 | K21: 45792 | L21: 2298473 | N21: 45790 | O21: 651 | S21: 44317 | T21: 468.725 | U21: =T21/T20-1 -> 0.033229781 | V21: =T21/T9-1 -> 0.48844729 | Z21: 44317 | AA21: 139.10437 | AD21: 45383 | AE21: 668672.71 | AF21: =AE21/AE17-1 -> -0.051556447 | AH21: 2027 | AJ21: 0.04
A22: 45790 | B22: 1140.92 | D22: 45791 | E22: 1140.92 | K22: 45791 | L22: 2301643.2 | N22: 45789 | O22: 650 | S22: 44348 | T22: 483.6049 | U22: =T22/T21-1 -> 0.03174548 | V22: =T22/T10-1 -> 0.50200078 | Z22: 44348 | AA22: 141.74208 | AD22: 45474 | AE22: 720760.48 | AF22: =AE22/AE18-1 -> -0.017167772 | AH22: 2028 | AJ22: 0.032
A23: 45789 | B23: 1141.2 | D23: 45790 | E23: 1140.92 | K23: 45790 | L23: 2285483.2 | N23: 45786 | O23: 678 | S23: 44378 | T23: 498.0987 | U23: =T23/T22-1 -> 0.029970333 | V23: =T23/T11-1 -> 0.51766172 | Z23: 44378 | AA23: 141.54961 | AD23: 45566 | AE23: 708557 | AF23: =AE23/AE19-1 -> -0.020234764 | AH23: 2029 | AJ23: 0.031
A24: 45786 | B24: 1144.11 | D24: 45789 | E24: 1141.2 | K24: 45789 | L24: 2230394.8 | N24: 45785 | O24: 678 | S24: 44409 | T24: 510.3942 | U24: =T24/T23-1 -> 0.024684867 | V24: =T24/T12-1 -> 0.51423887 | Z24: 44409 | AA24: 143.43631 | AD24: 45627 | AE24: 710734.7 | AF24: =AE24/AE20-1 -> 0.02074193 | AH24: 2030 | AJ24: 0.03
A25: 45785 | B25: 1143.32 | D25: 45786 | E25: 1144.11 | K25: 45786 | L25: 2114385.5 | N25: 45784 | O25: 766 | S25: 44440 | T25: 528.4968 | U25: =T25/T24-1 -> 0.03546788 | V25: =T25/T13-1 -> 0.52471217 | Z25: 44440 | AA25: 144.04418
A26: 45784 | B26: 1156.07 | D26: 45785 | E26: 1143.32 | K26: 45785 | L26: 2061722.2 | N26: 45783 | O26: 741 | S26: 44470 | T26: 547.0802 | U26: =T26/T25-1 -> 0.035162748 | V26: =T26/T14-1 -> 0.52111651 | Z26: 44470 | AA26: 143.53112
A27: 45783 | B27: 1199.61 | D27: 45784 | E27: 1156.07 | K27: 45784 | L27: 2059914.9 | N27: 45782 | O27: 741 | S27: 44501 | T27: 560.9184 | U27: =T27/T26-1 -> 0.025294646 | V27: =T27/T15-1 -> 0.51182345 | Z27: 44501 | AA27: 145.86834
A28: 45782 | B28: 1202.92 | D28: 45783 | E28: 1199.61 | K28: 45783 | L28: 2129994.5 | N28: 45779 | O28: 741 | S28: 44531 | T28: 582.4575 | U28: =T28/T27-1 -> 0.038399703 | V28: =T28/T16-1 -> 0.50941634 | Z28: 44531 | AA28: 149.82457
A29: 45779 | B29: 1183.37 | D29: 45782 | E29: 1202.92 | K29: 45782 | L29: 2059931.6 | N29: 45778 | O29: 735 | S29: 44562 | T29: 605.0317 | U29: =T29/T28-1 -> 0.038756819 | V29: =T29/T17-1 -> 0.50690162 | Z29: 44562 | AA29: 148.19264
A30: 45778 | B30: 1183.37 | D30: 45779 | E30: 1183.37 | K30: 45777 | L30: 2100843.8 | N30: 45777 | O30: 726 | S30: 44593 | T30: 633.4341 | U30: =T30/T29-1 -> 0.046943656 | V30: =T30/T18-1 -> 0.52319257 | Z30: 44593 | AA30: 149.89959
A31: 45777 | B31: 1183.37 | D31: 45778 | E31: 1183.37 | K31: 45776 | L31: 2158847.8 | N31: 45776 | O31: 701 | S31: 44621 | T31: 676.0566 | U31: =T31/T30-1 -> 0.067287978 | V31: =T31/T19-1 -> 0.5510663 | Z31: 44621 | AA31: 149.58
A32: 45776 | B32: 1173.15 | D32: 45777 | E32: 1183.37 | K32: 45775 | L32: 2179248.8 | N32: 45775 | O32: 710 | S32: 44652 | T32: 716.9399 | U32: =T32/T31-1 -> 0.060473191 | V32: =T32/T20-1 -> 0.58038009 | Z32: 44652 | AA32: 150.80114
A33: 45775 | B33: 1176.55 | D33: 45776 | E33: 1173.15 | K33: 45772 | L33: 2225242.8 | N33: 45772 | O33: 692 | S33: 44682 | T33: 753.147 | U33: =T33/T32-1 -> 0.050502281 | V33: =T33/T21-1 -> 0.6067993 | Z33: 44682 | AA33: 150.93255
A34: 45772 | B34: 1184.24 | D34: 45775 | E34: 1176.55 | K34: 45771 | L34: 2232745.2 | N34: 45771 | O34: 713 | S34: 44713 | T34: 793.0278 | U34: =T34/T33-1 -> 0.052952213 | V34: =T34/T22-1 -> 0.63982582 | Z34: 44713 | AA34: 152.48435
A35: 45771 | B35: 1186.53 | D35: 45772 | E35: 1184.24 | K35: 45770 | L35: 2239402 | N35: 45770 | O35: 720 | S35: 44743 | T35: 851.761 | U35: =T35/T34-1 -> 0.074061969 | V35: =T35/T23-1 -> 0.71002454 | Z35: 44743 | AA35: 151.4232
A36: 45770 | B36: 1168 | D36: 45771 | E36: 1186.53 | K36: 45769 | L36: 2163891 | N36: 45769 | O36: 720 | S36: 44774 | T36: 911.1316 | U36: =T36/T35-1 -> 0.069703356 | V36: =T36/T24-1 -> 0.78515273 | Z36: 44774 | AA36: 150.86399
... A67: 45727 | B67: 1230.38 | D67: 45728 | E67: 1229.34 | K67: 45716 | L67: 2205800.5 | N67: 45723 | O67: 692 | S67: 45717 | T67: 8353.3158 | U67: =T67/T66-1 -> 0.037293353 | V67: =T67/T55-1 -> 0.55930016 | Z67: 45717 | AA67: 149.89801
A68: 45726 | B68: 1228.92 | D68: 45727 | E68: 1230.38 | K68: 45715 | L68: 2193656.8 | N68: 45722 | O68: 714 | S68: 45748 | T68: 8585.6078 | U68: =T68/T67-1 -> 0.027808358 | V68: =T68/T56-1 -> 0.47260264 | Z68: 45748
A69: 45723 | B69: 1221.93 | D69: 45726 | E69: 1228.92 | K69: 45714 | L69: 2275036.8 | N69: 45721 | O69: 717
A70: 45722 | B70: 1237.86 | D70: 45723 | E70: 1221.93 | K70: 45713 | L70: 2282898.8 | N70: 45720 | O70: 780
A71: 45721 | B71: 1235.31 | D71: 45722 | E71: 1237.86 | K71: 45712 | L71: 2348398.5 | N71: 45719 | O71: 780
A72: 45720 | B72: 1228.48 | D72: 45721 | E72: 1235.31 | K72: 45709 | L72: 2364529.5 | N72: 45716 | O72: 780
A73: 45719 | B73: 1228.48 | D73: 45720 | E73: 1228.48 | K73: 45708 | L73: 2410221 | N73: 45715 | O73: 769
A74: 45716 | B74: 1228.48 | D74: 45719 | E74: 1228.48 | K74: 45707 | L74: 2401579.8 | N74: 45714 | O74: 749
A75: 45715 | B75: 1215.29 | D75: 45716 | E75: 1228.48 | K75: 45706 | L75: 2391724.8 | N75: 45713 | O75: 748
A76: 45714 | B76: 1211.56 | D76: 45715 | E76: 1215.29 | K76: 45705 | L76: 2254188.8 | N76: 45712 | O76: 730
A77: 45713 | B77: 1211.96 | D77: 45714 | E77: 1211.56 | K77: 45702 | L77: 2387385.8 | N77: 45709 | O77: 720
A78: 45712 | B78: 1207.48 | D78: 45713 | E78: 1211.96 | K78: 45701 | L78: 2353743.8 | N78: 45708 | O78: 719
A79: 45709 | B79: 1205.88 | D79: 45712 | E79: 1207.48 | K79: 45700 | L79: 2285846.5 | N79: 45707 | O79: 719
A80: 45708 | B80: 1206.06 | D80: 45709 | E80: 1205.88 | K80: 45699 | L80: 2273568 | N80: 45706 | O80: 696
... A249: 45471 | B249: 1347.96 | D249: 45474 | E249: 1413.01 | K249: 45449 | L249: 1503728.4 | N249: 45469 | O249: 1429
A250: 45470 | B250: 1331.96 | D250: 45471 | E250: 1347.96 | N250: 45468 | O250: 1440
A251: 45469 | B251: 1332.13 | D251: 45470 | E251: 1331.96 | N251: 45467 | O251: 1443
A252: 45468 | B252: 1308.99 | D252: 45469 | E252: 1332.13 | N252: 45464 | O252: 1420
A253: 45467 | B253: 1295.22 | D253: 45468 | E253: 1308.99 | N253: 45463 | O253: 1402
A254: 45464 | B254: 1273.81 | D254: 45467 | E254: 1295.22 | N254: 45462 | O254: 1384
A255: 45463 | B255: 1273.81 | D255: 45464 | E255: 1273.81 | N255: 45461 | O255: 1385
A256: 45462 | B256: 1273.81 | D256: 45463 | E256: 1273.81 | N256: 45460 | O256: 1382
A257: 45461 | B257: 1245.49 | D257: 45462 | E257: 1273.81 | N257: 45457 | O257: 1382
A258: 45460 | B258: 1244.64 | D258: 45461 | E258: 1245.49 | N258: 45456 | O258: 1421
A259: 45457 | B259: 1244.64 | D259: 45460 | E259: 1244.64 | N259: 45455 | O259: 1484
A260: 45456 | B260: 1241.1 | D260: 45457 | E260: 1244.64 | N260: 45454 | O260: 1525
A261: 45455 | B261: 1278.94 | D261: 45456 | E261: 1241.1 | N261: 45453 | O261: 1488
... A263: 45453 | B263: 1272.63 | D263: 45454 | E263: 1273.9 | N263: 45449 | O263: 1596
A264: 45450 | B264: 1282.33 | D264: 45453 | E264: 1272.63
A265: 45449 | B265: 1272.01 | D265: 45450 | E265: 1282.33
D266: 45449 | E266: 1272.01
D267: 45448 | E267: 1283.09
D268: 45447 | E268: 1280.8
D269: 45446 | E269: 1269.91
D270: 45443 | E270: 1215.93
D271: 45442 | E271: 1182.71
D272: 45441 | E272: 1177.14
D273: 45440 | E273: 1200.9
D274: 45439 | E274: 1228.18
D275: 45436 | E275: 1205.73
D276: 45435 | E276: 1234.4
D277: 45434 | E277: 1230.6
... D1581: 43910 | E1581: 91.4

Sheet 1) Estadística
A9: Fecha | B9: AGRO $ | C9: Merval $ | D9: Rend AGRO | E9: Rend Merval | F9: MEP | G9: AGRO USD | H9: Merval USD | I9: Rend AGRO2 | J9: Rend Merval3 | K9: Riesgo país
A10: 45814 | B10: 48.2 | C10: =VLOOKUP(Tabla1[[#This Row],[Fecha]],[1]Base!$K$5:$L$249,2,FALSE) -> 2156778.5 | D10: =LN(B10/B11) -> 0.0093799541 | E10: =LN(C10/C11) -> 0.015241126 | F10: 1192.4 | G10: =B10/F10 -> 0.040422677 | H10: =Tabla1[[#This Row],[Merval $]]/F10 -> 1808.771 | I10: =LN(G10/G11) -> 0.0093631811 | J10: =LN(H10/H11) -> 0.015224353 | K10: =VLOOKUP(Tabla1[[#This Row],[Fecha]],[1]Base!$N$5:$O$263,2,FALSE) -> 688
A11: 45813 | B11: 47.75 | C11: =VLOOKUP(Tabla1[[#This Row],[Fecha]],[1]Base!$K$5:$L$249,2,FALSE) -> 2124156 | D11: =LN(B11/B12) -> -0.025841231 | E11: =LN(C11/C12) -> -0.0012981436 | F11: =VLOOKUP(A11,[1]Base!$A$5:$B$265, 2, FALSE) -> 1192.38 | G11: =B11/F11 -> 0.040045959 | H11: =Tabla1[[#This Row],[Merval $]]/F11 -> 1781.4422 | I11: =LN(G11/G12) -> -0.025137006 | J11: =LN(H11/H12) -> -0.00059391818 | K11: =VLOOKUP(Tabla1[[#This Row],[Fecha]],[1]Base!$N$5:$O$263,2,FALSE) -> 688
A12: 45812 | B12: 49 | C12: =VLOOKUP(Tabla1[[#This Row],[Fecha]],[1]Base!$K$5:$L$249,2,FALSE) -> 2126915.2 | D12: =LN(B12/B13) -> -0.055569851 | E12: =LN(C12/C13) -> -0.044921515 | F12: =VLOOKUP(A12,[1]Base!$A$5:$B$265, 2, FALSE) -> 1193.22 | G12: =B12/F12 -> 0.041065353 | H12: =Tabla1[[#This Row],[Merval $]]/F12 -> 1782.5005 | I12: =LN(G12/G13) -> -0.058549429 | J12: =LN(H12/H13) -> -0.047901093 | K12: =VLOOKUP(Tabla1[[#This Row],[Fecha]],[1]Base!$N$5:$O$263,2,FALSE) -> 688
A13: 45811 | B13: 51.8 | C13: =VLOOKUP(Tabla1[[#This Row],[Fecha]],[1]Base!$K$5:$L$249,2,FALSE) -> 2224638 | D13: =LN(B13/B14) -> 0.053531114 | E13: =LN(C13/C14) -> 0.0082812673 | F13: =VLOOKUP(A13,[1]Base!$A$5:$B$265, 2, FALSE) -> 1189.67 | G13: =B13/F13 -> 0.043541486 | H13: =Tabla1[[#This Row],[Merval $]]/F13 -> 1869.9623 | I13: =LN(G13/G14) -> 0.048567865 | J13: =LN(H13/H14) -> 0.003318018 | K13: =VLOOKUP(Tabla1[[#This Row],[Fecha]],[1]Base!$N$5:$O$263,2,FALSE) -> 668
A14: 45810 | B14: 49.1 | C14: =VLOOKUP(Tabla1[[#This Row],[Fecha]],[1]Base!$K$5:$L$249,2,FALSE) -> 2206291.2 | D14: =LN(B14/B15) -> -0.045779138 | E14: =LN(C14/C15) -> -0.032420082 | F14: =VLOOKUP(A14,[1]Base!$A$5:$B$265, 2, FALSE) -> 1183.78 | G14: =B14/F14 -> 0.041477302 | H14: =Tabla1[[#This Row],[Merval $]]/F14 -> 1863.768 | I14: =LN(G14/G15) -> -0.039094204 | J14: =LN(H14/H15) -> -0.025735149 | K14: =VLOOKUP(Tabla1[[#This Row],[Fecha]],[1]Base!$N$5:$O$263,2,FALSE) -> #N/A
A15: 45807 | B15: 51.4 | C15: =VLOOKUP(Tabla1[[#This Row],[Fecha]],[1]Base!$K$5:$L$249,2,FALSE) -> 2278991.5 | D15: =LN(B15/B16) -> -0.038172574 | E15: =LN(C15/C16) -> -0.012672483 | F15: =VLOOKUP(A15,[1]Base!$A$5:$B$265, 2, FALSE) -> 1191.72 | G15: =B15/F15 -> 0.043130937 | H15: =Tabla1[[#This Row],[Merval $]]/F15 -> 1912.3548 | I15: =LN(G15/G16) -> -0.046446902 | J15: =LN(H15/H16) -> -0.020946812 | K15: =VLOOKUP(Tabla1[[#This Row],[Fecha]],[1]Base!$N$5:$O$263,2,FALSE) -> #N/A
A16: 45806 | B16: 53.4 | C16: =VLOOKUP(Tabla1[[#This Row],[Fecha]],[1]Base!$K$5:$L$249,2,FALSE) -> 2308055.8 | D16: =LN(B16/B17) -> 0 | E16: =LN(C16/C17) -> -0.01559393 | F16: =VLOOKUP(A16,[1]Base!$A$5:$B$265, 2, FALSE) -> 1181.9 | G16: =B16/F16 -> 0.045181487 | H16: =Tabla1[[#This Row],[Merval $]]/F16 -> 1952.8351 | I16: =LN(G16/G17) -> -0.014573915 | J16: =LN(H16/H17) -> -0.030167845 | K16: =VLOOKUP(Tabla1[[#This Row],[Fecha]],[1]Base!$N$5:$O$263,2,FALSE) -> 663
A17: 45805 | B17: 53.4 | C17: =VLOOKUP(Tabla1[[#This Row],[Fecha]],[1]Base!$K$5:$L$249,2,FALSE) -> 2344329.5 | D17: =LN(B17/B18) -> -0.0018709079 | E17: =LN(C17/C18) -> -0.0045830128 | F17: =VLOOKUP(A17,[1]Base!$A$5:$B$265, 2, FALSE) -> 1164.8 | G17: =B17/F17 -> 0.04584478 | H17: =Tabla1[[#This Row],[Merval $]]/F17 -> 2012.6455 | I17: =LN(G17/G18) -> -0.0048802391 | J17: =LN(H17/H18) -> -0.007592344 | K17: =VLOOKUP(Tabla1[[#This Row],[Fecha]],[1]Base!$N$5:$O$263,2,FALSE) -> 655
A18: 45804 | B18: 53.5 | C18: =VLOOKUP(Tabla1[[#This Row],[Fecha]],[1]Base!$K$5:$L$249,2,FALSE) -> 2355098.2 | D18: =LN(B18/B19) -> 0.030362864 | E18: =LN(C18/C19) -> -0.0066450046 | F18: =VLOOKUP(A18,[1]Base!$A$5:$B$265, 2, FALSE) -> 1161.3 | G18: =B18/F18 -> 0.046069061 | H18: =Tabla1[[#This Row],[Merval $]]/F18 -> 2027.9844 | I18: =LN(G18/G19) -> 0.016594178 | J18: =LN(H18/H19) -> -0.02041369 | K18: =VLOOKUP(Tabla1[[#This Row],[Fecha]],[1]Base!$N$5:$O$263,2,FALSE) -> 666
A19: 45803 | B19: 51.9 | C19: =VLOOKUP(Tabla1[[#This Row],[Fecha]],[1]Base!$K$5:$L$249,2,FALSE) -> 2370800 | D19: =LN(B19/B20) -> -0.0057637047 | E19: =LN(C19/C20) -> 0.010557368 | F19: =VLOOKUP(A19,[1]Base!$A$5:$B$265, 2, FALSE) -> 1145.42 | G19: =B19/F19 -> 0.04531089 | H19: =Tabla1[[#This Row],[Merval $]]/F19 -> 2069.8085 | I19: =LN(G19/G20) -> -0.0075987761 | J19: =LN(H19/H20) -> 0.0087222969 | K19: =VLOOKUP(Tabla1[[#This Row],[Fecha]],[1]Base!$N$5:$O$263,2,FALSE) -> 666
A20: 45800 | B20: 52.2 | C20: =VLOOKUP(Tabla1[[#This Row],[Fecha]],[1]Base!$K$5:$L$249,2,FALSE) -> 2345902.2 | D20: =LN(B20/B21) -> -0.015209419 | E20: =LN(C20/C21) -> 0.013304889 | F20: =VLOOKUP(A20,[1]Base!$A$5:$B$265, 2, FALSE) -> 1143.32 | G20: =B20/F20 -> 0.045656509 | H20: =Tabla1[[#This Row],[Merval $]]/F20 -> 2051.8335 | I20: =LN(G20/G21) -> -0.01506074 | J20: =LN(H20/H21) -> 0.013453567 | K20: =VLOOKUP(Tabla1[[#This Row],[Fecha]],[1]Base!$N$5:$O$263,2,FALSE) -> 665
A21: 45799 | B21: 53 | C21: =VLOOKUP(Tabla1[[#This Row],[Fecha]],[1]Base!$K$5:$L$249,2,FALSE) -> 2314897 | D21: =LN(B21/B22) -> 0.009478744 | E21: =LN(C21/C22) -> -0.0020073606 | F21: =VLOOKUP(A21,[1]Base!$A$5:$B$265, 2, FALSE) -> 1143.49 | G21: =B21/F21 -> 0.046349334 | H21: =Tabla1[[#This Row],[Merval $]]/F21 -> 2024.4139 | I21: =LN(G21/G22) -> 0.014111674 | J21: =LN(H21/H22) -> 0.0026255694 | K21: =VLOOKUP(Tabla1[[#This Row],[Fecha]],[1]Base!$N$5:$O$263,2,FALSE) -> 665
A22: 45798 | B22: 52.5 | C22: =VLOOKUP(Tabla1[[#This Row],[Fecha]],[1]Base!$K$5:$L$249,2,FALSE) -> 2319548.5 | D22: =LN(B22/B23) -> -0.037387532 | E22: =LN(C22/C23) -> -0.025082347 | F22: =VLOOKUP(A22,[1]Base!$A$5:$B$265, 2, FALSE) -> 1148.8 | G22: =B22/F22 -> 0.045699861 | H22: =Tabla1[[#This Row],[Merval $]]/F22 -> 2019.1056 | I22: =LN(G22/G23) -> -0.033452041 | J22: =LN(H22/H23) -> -0.021146856 | K22: =VLOOKUP(Tabla1[[#This Row],[Fecha]],[1]Base!$N$5:$O$263,2,FALSE) -> 661
... A40: 45770 | B40: 43.45 | C40: =VLOOKUP(Tabla1[[#This Row],[Fecha]],[1]Base!$K$5:$L$249,2,FALSE) -> 2239402 | D40: =LN(B40/B41) -> 0.031563111 | E40: =LN(C40/C41) -> 0.034300876 | F40: =VLOOKUP(A40,[1]Base!$A$5:$B$265, 2, FALSE) -> 1168 | G40: =B40/F40 -> 0.037200342 | H40: =Tabla1[[#This Row],[Merval $]]/F40 -> 1917.2962 | I40: =LN(G40/G41) -> 0.0076317668 | J40: =LN(H40/H41) -> 0.010369532 | K40: =VLOOKUP(Tabla1[[#This Row],[Fecha]],[1]Base!$N$5:$O$263,2,FALSE) -> 720
A41: 45769 | B41: 42.1 | C41: =VLOOKUP(Tabla1[[#This Row],[Fecha]],[1]Base!$K$5:$L$249,2,FALSE) -> 2163891 | D41: =LN(B41/B42) -> -0.019988908 | E41: =LN(C41/C42) -> 0.056164353 | F41: =VLOOKUP(A41,[1]Base!$A$5:$B$265, 2, FALSE) -> 1140.38 | G41: =B41/F41 -> 0.036917519 | H41: =Tabla1[[#This Row],[Merval $]]/F41 -> 1897.5175 | I41: =LN(G41/G42) -> -0.036166342 | J41: =LN(H41/H42) -> 0.039986919 | K41: =VLOOKUP(Tabla1[[#This Row],[Fecha]],[1]Base!$N$5:$O$263,2,FALSE) -> 720 | P41: AGRO | R41: S&P | V41: AGRO
A42: 45768 | B42: 42.95 | C42: =VLOOKUP(Tabla1[[#This Row],[Fecha]],[1]Base!$K$5:$L$249,2,FALSE) -> 2045707.4 | D42: =LN(B42/B43) -> -0.11012215 | E42: =LN(C42/C43) -> -0.062651909 | F42: =VLOOKUP(A42,[1]Base!$A$5:$B$265, 2, FALSE) -> 1122.08 | G42: =B42/F42 -> 0.038277128 | H42: =Tabla1[[#This Row],[Merval $]]/F42 -> 1823.1386 | I42: =LN(G42/G43) -> -0.071787207 | J42: =LN(H42/H43) -> -0.024316963 | K42: =VLOOKUP(Tabla1[[#This Row],[Fecha]],[1]Base!$N$5:$O$263,2,FALSE) -> 720 | P42: $ | Q42: USD | R42: $ | S42: USD | V42: $ | W42: USD
A43: 45763 | B43: 47.95 | C43: =VLOOKUP(Tabla1[[#This Row],[Fecha]],[1]Base!$K$5:$L$249,2,FALSE) -> 2177975 | D43: =LN(B43/B44) -> -0.10765194 | E43: =LN(C43/C44) -> -0.047655111 | F43: =VLOOKUP(A43,[1]Base!$A$5:$B$265, 2, FALSE) -> 1165.93 | G43: =B43/F43 -> 0.041125968 | H43: =Tabla1[[#This Row],[Merval $]]/F43 -> 1868.0152 | I43: =LN(G43/G44) -> -0.047754601 | J43: =LN(H43/H44) -> 0.012242232 | K43: =VLOOKUP(Tabla1[[#This Row],[Fecha]],[1]Base!$N$5:$O$263,2,FALSE) -> 745 | O43: Curtosis | P43: =KURT(Tabla1[Rend AGRO]) -> 1.5011416 | Q43: =KURT(I10:I255) -> 1.5007314 | R43: =KURT(E10:E255) -> 2.3075668 | S43: =KURT(J10:J255) -> 1.6945733 | U43: Min | V43: =INDEX(Tabla1[Fecha],MATCH(MIN(Tabla1[AGRO $]),Tabla1[AGRO $],0)) -> 45782 | W43: =INDEX(Tabla1[Fecha],MATCH(MIN(Tabla1[AGRO USD]),Tabla1[AGRO USD],0)) -> 45757
A44: 45762 | B44: 53.4 | C44: =VLOOKUP(Tabla1[[#This Row],[Fecha]],[1]Base!$K$5:$L$249,2,FALSE) -> 2284279.5 | D44: =LN(B44/B45) -> 0.0037523496 | E44: =LN(C44/C45) -> -0.034706223 | F44: =VLOOKUP(A44,[1]Base!$A$5:$B$265, 2, FALSE) -> 1237.9 | G44: =B44/F44 -> 0.043137572 | H44: =Tabla1[[#This Row],[Merval $]]/F44 -> 1845.286 | I44: =LN(G44/G45) -> 0.016195813 | J44: =LN(H44/H45) -> -0.022262759 | K44: =VLOOKUP(Tabla1[[#This Row],[Fecha]],[1]Base!$N$5:$O$263,2,FALSE) -> 725 | O44: Simetría | P44: =_xlfn.SKEW.P(D10:D254) -> 0.507734 | Q44: =_xlfn.SKEW.P(I10:I254) -> 0.68153452 | R44: =_xlfn.SKEW.P(E10:E254) -> -0.40569141 | S44: =_xlfn.SKEW.P(J10:J254) -> 0.23074705 | U44: Max | V44: =INDEX(Tabla1[Fecha],MATCH(MAX(Tabla1[AGRO $]),Tabla1[AGRO $],0)) -> 45643 | W44: =INDEX(Tabla1[Fecha],MATCH(MAX(Tabla1[AGRO USD]),Tabla1[AGRO USD],0)) -> 45629
A45: 45761 | B45: 53.2 | C45: =VLOOKUP(Tabla1[[#This Row],[Fecha]],[1]Base!$K$5:$L$249,2,FALSE) -> 2364950 | D45: =LN(B45/B46) -> 0.080199362 | E45: =LN(C45/C46) -> 0.050358805 | F45: =VLOOKUP(A45,[1]Base!$A$5:$B$265, 2, FALSE) -> 1253.4 | G45: =B45/F45 -> 0.042444551 | H45: =Tabla1[[#This Row],[Merval $]]/F45 -> 1886.8278 | I45: =LN(G45/G46) -> 0.14201908 | J45: =LN(H45/H46) -> 0.11217852 | K45: =VLOOKUP(Tabla1[[#This Row],[Fecha]],[1]Base!$N$5:$O$263,2,FALSE) -> 896 | O45: Observaciones | P45: =COUNT(D10:D254) -> 245 | Q45: =COUNT(I10:I254) -> 245 | R45: =COUNT(E10:E254) -> 245 | S45: =COUNT(J10:J254) -> 245
A46: 45758 | B46: 49.1 | C46: =VLOOKUP(Tabla1[[#This Row],[Fecha]],[1]Base!$K$5:$L$249,2,FALSE) -> 2248803 | D46: =LN(B46/B47) -> 0.073951318 | E46: =LN(C46/C47) -> 0.063004097 | F46: =VLOOKUP(A46,[1]Base!$A$5:$B$265, 2, FALSE) -> 1333.33 | G46: =B46/F46 -> 0.036825092 | H46: =Tabla1[[#This Row],[Merval $]]/F46 -> 1686.6065 | I46: =LN(G46/G47) -> 0.096700637 | J46: =LN(H46/H47) -> 0.085753415 | K46: =VLOOKUP(Tabla1[[#This Row],[Fecha]],[1]Base!$N$5:$O$263,2,FALSE) -> 874 | O46: Jarque- Bera | P46: =(P45/6)*(P44^2+(P43^2)/4) -> 33.530307 | Q46: =(Q45/6)*(Q44^2+(Q43^2)/4) -> 41.957801 | R46: =(R45/6)*(R44^2+(R43^2)/4) -> 61.078566 | S46: =(S45/6)*(S44^2+(S43^2)/4) -> 31.488169
A47: 45757 | B47: 45.6 | C47: =VLOOKUP(Tabla1[[#This Row],[Fecha]],[1]Base!$K$5:$L$249,2,FALSE) -> 2111490.2 | D47: =LN(B47/B48) -> -0.063715814 | E47: =LN(C47/C48) -> -0.03357038 | F47: =VLOOKUP(A47,[1]Base!$A$5:$B$265, 2, FALSE) -> 1364.01 | G47: =B47/F47 -> 0.03343084 | H47: =Tabla1[[#This Row],[Merval $]]/F47 -> 1548.002 | I47: =LN(G47/G48) -> -0.080192332 | J47: =LN(H47/H48) -> -0.050046898 | K47: =VLOOKUP(Tabla1[[#This Row],[Fecha]],[1]Base!$N$5:$O$263,2,FALSE) -> 899 | O47: p-value | P47: =_xlfn.CHISQ.DIST(P46,2,) -> 2.6179204e-08 | Q47: =_xlfn.CHISQ.DIST(Q46,2,) -> 3.8721237e-10 | R47: =_xlfn.CHISQ.DIST(R46,2,) -> 2.7285243e-14 | S47: =_xlfn.CHISQ.DIST(S46,2,) -> 7.267767e-08
A48: 45756 | B48: 48.6 | C48: =VLOOKUP(Tabla1[[#This Row],[Fecha]],[1]Base!$K$5:$L$249,2,FALSE) -> 2183577 | D48: =LN(B48/B49) -> 0.025001302 | E48: =LN(C48/C49) -> 0.092517582 | F48: =VLOOKUP(A48,[1]Base!$A$5:$B$265, 2, FALSE) -> 1341.72 | G48: =B48/F48 -> 0.036222163 | H48: =Tabla1[[#This Row],[Merval $]]/F48 -> 1627.4461 | I48: =LN(G48/G49) -> 0.050651092 | J48: =LN(H48/H49) -> 0.11816737 | K48: =VLOOKUP(Tabla1[[#This Row],[Fecha]],[1]Base!$N$5:$O$263,2,FALSE) -> 889
A49: 45755 | B49: 47.4 | C49: =VLOOKUP(Tabla1[[#This Row],[Fecha]],[1]Base!$K$5:$L$249,2,FALSE) -> 1990621.2 | D49: =LN(B49/B50) -> 0.015949301 | E49: =LN(C49/C50) -> -0.017600465 | F49: =VLOOKUP(A49,[1]Base!$A$5:$B$265, 2, FALSE) -> 1376.58 | G49: =B49/F49 -> 0.03443316 | H49: =Tabla1[[#This Row],[Merval $]]/F49 -> 1446.0629 | I49: =LN(G49/G50) -> 0.011413321 | J49: =LN(H49/H50) -> -0.022136446 | K49: =VLOOKUP(Tabla1[[#This Row],[Fecha]],[1]Base!$N$5:$O$263,2,FALSE) -> 978 | O49: Rendimiento diario | P49: =AVERAGE(D10:D254) -> -0.00043342876 | Q49: =AVERAGE(I9:I253) -> -0.00032404155 | R49: =AVERAGE(E10:E254) -> 0.0014721145 | S49: =AVERAGE(J10:J254) -> 0.0017359115 | V49: S&P
A50: 45754 | B50: 46.65 | C50: =VLOOKUP(Tabla1[[#This Row],[Fecha]],[1]Base!$K$5:$L$249,2,FALSE) -> 2025967.2 | D50: =LN(B50/B51) -> -0.062325463 | E50: =LN(C50/C51) -> -0.0396051 | F50: =VLOOKUP(A50,[1]Base!$A$5:$B$265, 2, FALSE) -> 1370.35 | G50: =B50/F50 -> 0.034042398 | H50: =Tabla1[[#This Row],[Merval $]]/F50 -> 1478.4305 | I50: =LN(G50/G51) -> -0.084393727 | J50: =LN(H50/H51) -> -0.061673363 | K50: =VLOOKUP(Tabla1[[#This Row],[Fecha]],[1]Base!$N$5:$O$263,2,FALSE) -> 960 | O50: Desviación | P50: =STDEV(D10:D254) -> 0.035781413 | Q50: =STDEV(I10:I254) -> 0.037594211 | R50: =STDEV(E10:E254) -> 0.027062429 | S50: =STDEV(J10:J254) -> 0.029370398 | V50: $ | W50: USD
A51: 45751 | B51: 49.65 | C51: =VLOOKUP(Tabla1[[#This Row],[Fecha]],[1]Base!$K$5:$L$249,2,FALSE) -> 2107816 | D51: =LN(B51/B52) -> -0.057717729 | E51: =LN(C51/C52) -> -0.076617231 | F51: =VLOOKUP(A51,[1]Base!$A$5:$B$265, 2, FALSE) -> 1340.44 | G51: =B51/F51 -> 0.037040076 | H51: =Tabla1[[#This Row],[Merval $]]/F51 -> 1572.4807 | I51: =LN(G51/G52) -> -0.073523401 | J51: =LN(H51/H52) -> -0.092422903 | K51: =VLOOKUP(Tabla1[[#This Row],[Fecha]],[1]Base!$N$5:$O$263,2,FALSE) -> 925 | O51: Min | P51: =MIN(Tabla1[AGRO $]) -> 40.45 | Q51: =MIN(G10:G255) -> 0.03343084 | R51: =MIN(Tabla1[Merval $]) -> 1411953.4 | S51: =MIN(H10:H255) -> 1055.2957 | U51: Min | V51: =INDEX(Tabla1[Fecha],MATCH(MIN(Tabla1[Merval $]),Tabla1[Merval $],0)) -> 45503 | W51: =INDEX(Tabla1[Fecha],MATCH(MIN(Tabla1[Merval USD]),Tabla1[Merval USD],0)) -> 45509
A52: 45750 | B52: 52.6 | C52: =VLOOKUP(Tabla1[[#This Row],[Fecha]],[1]Base!$K$5:$L$249,2,FALSE) -> 2275658.8 | D52: =LN(B52/B53) -> -0.03914759 | E52: =LN(C52/C53) -> -0.034920945 | F52: =VLOOKUP(A52,[1]Base!$A$5:$B$265, 2, FALSE) -> 1319.42 | G52: =B52/F52 -> 0.039866002 | H52: =Tabla1[[#This Row],[Merval $]]/F52 -> 1724.7417 | I52: =LN(G52/G53) -> -0.042906293 | J52: =LN(H52/H53) -> -0.038679649 | K52: =VLOOKUP(Tabla1[[#This Row],[Fecha]],[1]Base!$N$5:$O$263,2,FALSE) -> 872 | O52: Max | P52: =MAX(Tabla1[AGRO $]) -> 84 | Q52: =MAX(G10:G255) -> 0.077534514 | R52: =MAX(Tabla1[Merval $]) -> 2829730.5 | S52: =MAX(H10:H255) -> 2430.6432 | U52: Max | V52: =INDEX(Tabla1[Fecha],MATCH(MAX(Tabla1[Merval $]),Tabla1[Merval $],0)) -> 45666 | W52: =INDEX(Tabla1[Fecha],MATCH(MAX(Tabla1[Merval USD]),Tabla1[Merval USD],0)) -> 45666
A53: 45748 | B53: 54.7 | C53: =VLOOKUP(Tabla1[[#This Row],[Fecha]],[1]Base!$K$5:$L$249,2,FALSE) -> 2356530.8 | D53: =LN(B53/B54) -> -0.0018264845 | E53: =LN(C53/C54) -> 0.0075693212 | F53: =VLOOKUP(A53,[1]Base!$A$5:$B$265, 2, FALSE) -> 1314.47 | G53: =B53/F53 -> 0.04161373 | H53: =Tabla1[[#This Row],[Merval $]]/F53 -> 1792.7612 | I53: =LN(G53/G54) -> -0.0022069383 | J53: =LN(H53/H54) -> 0.0071888674 | K53: =VLOOKUP(Tabla1[[#This Row],[Fecha]],[1]Base!$N$5:$O$263,2,FALSE) -> 823 | O53: Beta | P53: {=INDEX(LINEST(D10:D254,E10:E254),1)} -> 0.87767651 | Q53: {=INDEX(LINEST(I10:I254,J10:J254),1)} -> 0.89453209
A54: 45747 | B54: 54.8 | C54: =VLOOKUP(Tabla1[[#This Row],[Fecha]],[1]Base!$K$5:$L$249,2,FALSE) -> 2338760.8 | D54: =LN(B54/B55) -> -0.025226563 | E54: =LN(C54/C55) -> -0.016875224 | F54: =VLOOKUP(A54,[1]Base!$A$5:$B$265, 2, FALSE) -> 1313.97 | G54: =B54/F54 -> 0.041705671 | H54: =Tabla1[[#This Row],[Merval $]]/F54 -> 1779.9194 | I54: =LN(G54/G55) -> -0.034040223 | J54: =LN(H54/H55) -> -0.025688884 | K54: =VLOOKUP(Tabla1[[#This Row],[Fecha]],[1]Base!$N$5:$O$263,2,FALSE) -> 816
A55: 45744 | B55: 56.2 | C55: =VLOOKUP(Tabla1[[#This Row],[Fecha]],[1]Base!$K$5:$L$249,2,FALSE) -> 2378562.8 | D55: =LN(B55/B56) -> -0.033248907 | E55: =LN(C55/C56) -> -0.013993649 | F55: =VLOOKUP(A55,[1]Base!$A$5:$B$265, 2, FALSE) -> 1302.44 | G55: =B55/F55 -> 0.04314978 | H55: =Tabla1[[#This Row],[Merval $]]/F55 -> 1826.2359 | I55: =LN(G55/G56) -> -0.041072497 | J55: =LN(H55/H56) -> -0.021817239 | K55: =VLOOKUP(Tabla1[[#This Row],[Fecha]],[1]Base!$N$5:$O$263,2,FALSE) -> 797
A56: 45743 | B56: 58.1 | C56: =VLOOKUP(Tabla1[[#This Row],[Fecha]],[1]Base!$K$5:$L$249,2,FALSE) -> 2412081.5 | D56: =LN(B56/B57) -> -0.0068610904 | E56: =LN(C56/C57) -> -0.01149414 | F56: =VLOOKUP(A56,[1]Base!$A$5:$B$265, 2, FALSE) -> 1292.29 | G56: =B56/F56 -> 0.044958949 | H56: =Tabla1[[#This Row],[Merval $]]/F56 -> 1866.5172 | I56: =LN(G56/G57) -> -0.0042798654 | J56: =LN(H56/H57) -> -0.0089129146 | K56: =VLOOKUP(Tabla1[[#This Row],[Fecha]],[1]Base!$N$5:$O$263,2,FALSE) -> 759
A57: 45742 | B57: 58.5 | C57: =VLOOKUP(Tabla1[[#This Row],[Fecha]],[1]Base!$K$5:$L$249,2,FALSE) -> 2439966.2 | D57: =LN(B57/B58) -> -0.020305266 | E57: =LN(C57/C58) -> -0.019366242 | F57: =VLOOKUP(A57,[1]Base!$A$5:$B$265, 2, FALSE) -> 1295.63 | G57: =B57/F57 -> 0.045151779 | H57: =Tabla1[[#This Row],[Merval $]]/F57 -> 1883.2277 | I57: =LN(G57/G58) -> -0.021332321 | J57: =LN(H57/H58) -> -0.020393296 | K57: =VLOOKUP(Tabla1[[#This Row],[Fecha]],[1]Base!$N$5:$O$263,2,FALSE) -> 769
A58: 45741 | B58: 59.7 | C58: =VLOOKUP(Tabla1[[#This Row],[Fecha]],[1]Base!$K$5:$L$249,2,FALSE) -> 2487679.8 | D58: =LN(B58/B59) -> -0.0083403319 | E58: =LN(C58/C59) -> 0.02200418 | F58: =VLOOKUP(A58,[1]Base!$A$5:$B$265, 2, FALSE) -> 1294.3 | G58: =B58/F58 -> 0.046125319 | H58: =Tabla1[[#This Row],[Merval $]]/F58 -> 1922.0272 | I58: =LN(G58/G59) -> -0.013825486 | J58: =LN(H58/H59) -> 0.016519026 | K58: =VLOOKUP(Tabla1[[#This Row],[Fecha]],[1]Base!$N$5:$O$263,2,FALSE) -> 761
A59: 45737 | B59: 60.2 | C59: =VLOOKUP(Tabla1[[#This Row],[Fecha]],[1]Base!$K$5:$L$249,2,FALSE) -> 2433538.2 | D59: =LN(B59/B60) -> 0.037229342 | E59: =LN(C59/C60) -> 0.030014111 | F59: =VLOOKUP(A59,[1]Base!$A$5:$B$265, 2, FALSE) -> 1287.22 | G59: =B59/F59 -> 0.046767452 | H59: =Tabla1[[#This Row],[Merval $]]/F59 -> 1890.5379 | I59: =LN(G59/G60) -> 0.037516742 | J59: =LN(H59/H60) -> 0.030301511 | K59: =VLOOKUP(Tabla1[[#This Row],[Fecha]],[1]Base!$N$5:$O$263,2,FALSE) -> 769
A60: 45736 | B60: 58 | C60: =VLOOKUP(Tabla1[[#This Row],[Fecha]],[1]Base!$K$5:$L$249,2,FALSE) -> 2361583 | D60: =LN(B60/B61) -> -0.032233495 | E60: =LN(C60/C61) -> -0.012810221 | F60: =VLOOKUP(A60,[1]Base!$A$5:$B$265, 2, FALSE) -> 1287.59 | G60: =B60/F60 -> 0.045045395 | H60: =Tabla1[[#This Row],[Merval $]]/F60 -> 1834.111 | I60: =LN(G60/G61) -> -0.033173677 | J60: =LN(H60/H61) -> -0.013750403 | K60: =VLOOKUP(Tabla1[[#This Row],[Fecha]],[1]Base!$N$5:$O$263,2,FALSE) -> 762
A61: 45735 | B61: 59.9 | C61: =VLOOKUP(Tabla1[[#This Row],[Fecha]],[1]Base!$K$5:$L$249,2,FALSE) -> 2392030 | D61: =LN(B61/B62) -> 0.013445581 | E61: =LN(C61/C62) -> 0.044229192 | F61: =VLOOKUP(A61,[1]Base!$A$5:$B$265, 2, FALSE) -> 1286.38 | G61: =B61/F61 -> 0.046564779 | H61: =Tabla1[[#This Row],[Merval $]]/F61 -> 1859.505 | I61: =LN(G61/G62) -> 0.023454559 | J61: =LN(H61/H62) -> 0.054238171 | K61: =VLOOKUP(Tabla1[[#This Row],[Fecha]],[1]Base!$N$5:$O$263,2,FALSE) -> 777
A62: 45734 | B62: 59.1 | C62: =VLOOKUP(Tabla1[[#This Row],[Fecha]],[1]Base!$K$5:$L$249,2,FALSE) -> 2288538 | D62: =LN(B62/B63) -> -0.03164294 | E62: =LN(C62/C63) -> -0.024928778 | F62: =VLOOKUP(A62,[1]Base!$A$5:$B$265, 2, FALSE) -> 1299.32 | G62: =B62/F62 -> 0.045485331 | H62: =Tabla1[[#This Row],[Merval $]]/F62 -> 1761.3352 | I62: =LN(G62/G63) -> -0.06986855 | J62: =LN(H62/H63) -> -0.063154388 | K62: =VLOOKUP(Tabla1[[#This Row],[Fecha]],[1]Base!$N$5:$O$263,2,FALSE) -> 787
A63: 45733 | B63: 61 | C63: =VLOOKUP(Tabla1[[#This Row],[Fecha]],[1]Base!$K$5:$L$249,2,FALSE) -> 2346305.5 | D63: =LN(B63/B64) -> 0.028264558 | E63: =LN(C63/C64) -> 0.004583957 | F63: =VLOOKUP(A63,[1]Base!$A$5:$B$265, 2, FALSE) -> 1250.59 | G63: =B63/F63 -> 0.048776977 | H63: =Tabla1[[#This Row],[Merval $]]/F63 -> 1876.1589 | I63: =LN(G63/G64) -> 0.017968571 | J63: =LN(H63/H64) -> -0.0057120305 | K63: =VLOOKUP(Tabla1[[#This Row],[Fecha]],[1]Base!$N$5:$O$263,2,FALSE) -> 750
A64: 45730 | B64: 59.3 | C64: =VLOOKUP(Tabla1[[#This Row],[Fecha]],[1]Base!$K$5:$L$249,2,FALSE) -> 2335574.8 | D64: =LN(B64/B65) -> 0.048368668 | E64: =LN(C64/C65) -> 0.04527932 | F64: =VLOOKUP(A64,[1]Base!$A$5:$B$265, 2, FALSE) -> 1237.78 | G64: =B64/F64 -> 0.047908352 | H64: =Tabla1[[#This Row],[Merval $]]/F64 -> 1886.9062 | I64: =LN(G64/G65) -> 0.044945407 | J64: =LN(H64/H65) -> 0.041856059 | K64: =VLOOKUP(Tabla1[[#This Row],[Fecha]],[1]Base!$N$5:$O$263,2,FALSE) -> 737
A65: 45729 | B65: 56.5 | C65: =VLOOKUP(Tabla1[[#This Row],[Fecha]],[1]Base!$K$5:$L$249,2,FALSE) -> 2232180 | D65: =LN(B65/B66) -> -0.0035335726 | E65: =LN(C65/C66) -> -0.018094031 | F65: =VLOOKUP(A65,[1]Base!$A$5:$B$265, 2, FALSE) -> 1233.55 | G65: =B65/F65 -> 0.045802764 | H65: =Tabla1[[#This Row],[Merval $]]/F65 -> 1809.5578 | I65: =LN(G65/G66) -> -0.0069523238 | J65: =LN(H65/H66) -> -0.021512783 | K65: =VLOOKUP(Tabla1[[#This Row],[Fecha]],[1]Base!$N$5:$O$263,2,FALSE) -> 748
... A113: 45659 | B113: 74.3 | C113: =VLOOKUP(Tabla1[[#This Row],[Fecha]],[1]Base!$K$5:$L$249,2,FALSE) -> 2695646.5 | D113: =LN(B113/B114) -> 0.030056907 | E113: =LN(C113/C114) -> -1.8548424e-07 | F113: =VLOOKUP(A113,[1]Base!$A$5:$B$265, 2, FALSE) -> 1162.12 | G113: =B113/F113 -> 0.063934878 | H113: =Tabla1[[#This Row],[Merval $]]/F113 -> 2319.5939 | I113: =LN(G113/G114) -> 0.037165099 | J113: =LN(H113/H114) -> 0.00025608268 | K113: =VLOOKUP(Tabla1[[#This Row],[Fecha]],[1]Base!$N$5:$O$263,2,FALSE) -> 610
A114: 45657 | B114: 72.1 | C114: 2695647 | D114: =LN(B114/B115) -> 0 | E114: =LN(C114/C115) -> 0.061983318 | F114: =VLOOKUP(A114,[1]Base!$A$5:$B$265, 2, FALSE) -> 1170.41 | G114: =B114/F114 -> 0.061602344 | H114: 2319 | I114: =LN(G114/G115) -> 0 | J114: =LN(H114/H115) -> 0.068835241 | K114: =VLOOKUP(Tabla1[[#This Row],[Fecha]],[1]Base!$N$5:$O$263,2,FALSE) -> 635
A115: 45656 | B115: 72.1 | C115: =VLOOKUP(Tabla1[[#This Row],[Fecha]],[1]Base!$K$5:$L$249,2,FALSE) -> 2533634.8 | D115: =LN(B115/B116) -> -0.040766514 | E115: =LN(C115/C116) -> -0.017182755 | F115: =VLOOKUP(A115,[1]Base!$A$5:$B$265, 2, FALSE) -> 1170.41 | G115: =B115/F115 -> 0.061602344 | H115: =Tabla1[[#This Row],[Merval $]]/F115 -> 2164.7412 | I115: =LN(G115/G116) -> -0.040638362 | J115: =LN(H115/H116) -> -0.017054603 | K115: =VLOOKUP(Tabla1[[#This Row],[Fecha]],[1]Base!$N$5:$O$263,2,FALSE) -> 635
A116: 45653 | B116: 75.1 | C116: =VLOOKUP(Tabla1[[#This Row],[Fecha]],[1]Base!$K$5:$L$249,2,FALSE) -> 2577545.8 | D116: =LN(B116/B117) -> -0.028873397 | E116: =LN(C116/C117) -> -0.0076688307 | F116: =VLOOKUP(A116,[1]Base!$A$5:$B$265, 2, FALSE) -> 1170.56 | G116: =B116/F116 -> 0.064157326 | H116: =Tabla1[[#This Row],[Merval $]]/F116 -> 2201.9766 | I116: =LN(G116/G117) -> -0.02859152 | J116: =LN(H116/H117) -> -0.0073869541 | K116: =VLOOKUP(Tabla1[[#This Row],[Fecha]],[1]Base!$N$5:$O$263,2,FALSE) -> 627
A117: 45652 | B117: 77.3 | C117: =VLOOKUP(Tabla1[[#This Row],[Fecha]],[1]Base!$K$5:$L$249,2,FALSE) -> 2597388.5 | D117: =LN(B117/B118) -> 0.0012944986 | E117: =LN(C117/C118) -> 0.018013042 | F117: =VLOOKUP(A117,[1]Base!$A$5:$B$265, 2, FALSE) -> 1170.89 | G117: =B117/F117 -> 0.066018157 | H117: =Tabla1[[#This Row],[Merval $]]/F117 -> 2218.3027 | I117: =LN(G117/G118) -> -0.0072137822 | J117: =LN(H117/H118) -> 0.0095047612 | K117: =VLOOKUP(Tabla1[[#This Row],[Fecha]],[1]Base!$N$5:$O$263,2,FALSE) -> 631
A118: 45650 | B118: 77.2 | C118: =VLOOKUP(Tabla1[[#This Row],[Fecha]],[1]Base!$K$5:$L$249,2,FALSE) -> 2551020.5 | D118: =LN(B118/B119) -> 0.0012961765 | E118: =LN(C118/C119) -> 0.01974165 | F118: =VLOOKUP(A118,[1]Base!$A$5:$B$265, 2, FALSE) -> 1160.97 | G118: =B118/F118 -> 0.06649612 | H118: =Tabla1[[#This Row],[Merval $]]/F118 -> 2197.3182 | I118: =LN(G118/G119) -> 0.0024411145 | J118: =LN(H118/H119) -> 0.020886588 | K118: =VLOOKUP(Tabla1[[#This Row],[Fecha]],[1]Base!$N$5:$O$263,2,FALSE) -> 649
A119: 45649 | B119: 77.1 | C119: =VLOOKUP(Tabla1[[#This Row],[Fecha]],[1]Base!$K$5:$L$249,2,FALSE) -> 2501153 | D119: =LN(B119/B120) -> -0.011605546 | E119: =LN(C119/C120) -> 0.013521207 | F119: =VLOOKUP(A119,[1]Base!$A$5:$B$265, 2, FALSE) -> 1162.3 | G119: =B119/F119 -> 0.066333993 | H119: =Tabla1[[#This Row],[Merval $]]/F119 -> 2151.8997 | I119: =LN(G119/G120) -> -0.02905012 | J119: =LN(H119/H120) -> -0.0039233665 | K119: =VLOOKUP(Tabla1[[#This Row],[Fecha]],[1]Base!$N$5:$O$263,2,FALSE) -> 649
A120: 45646 | B120: 78 | C120: =VLOOKUP(Tabla1[[#This Row],[Fecha]],[1]Base!$K$5:$L$249,2,FALSE) -> 2467562 | D120: =LN(B120/B121) -> 0.029930666 | E120: =LN(C120/C121) -> 0.019506778 | F120: =VLOOKUP(A120,[1]Base!$A$5:$B$265, 2, FALSE) -> 1142.2 | G120: =B120/F120 -> 0.068289266 | H120: =Tabla1[[#This Row],[Merval $]]/F120 -> 2160.359 | I120: =LN(G120/G121) -> 0.020244615 | J120: =LN(H120/H121) -> 0.0098207265 | K120: =VLOOKUP(Tabla1[[#This Row],[Fecha]],[1]Base!$N$5:$O$263,2,FALSE) -> 671
A121: 45645 | B121: 75.7 | C121: =VLOOKUP(Tabla1[[#This Row],[Fecha]],[1]Base!$K$5:$L$249,2,FALSE) -> 2419894.2 | D121: =LN(B121/B122) -> -0.058991461 | E121: =LN(C121/C122) -> -0.040938352 | F121: =VLOOKUP(A121,[1]Base!$A$5:$B$265, 2, FALSE) -> 1131.19 | G121: =B121/F121 -> 0.066920676 | H121: =Tabla1[[#This Row],[Merval $]]/F121 -> 2139.2465 | I121: =LN(G121/G122) -> -0.05896494 | J121: =LN(H121/H122) -> -0.040911832 | K121: =VLOOKUP(Tabla1[[#This Row],[Fecha]],[1]Base!$N$5:$O$263,2,FALSE) -> 663
A122: 45644 | B122: 80.3 | C122: =VLOOKUP(Tabla1[[#This Row],[Fecha]],[1]Base!$K$5:$L$249,2,FALSE) -> 2521016.5 | D122: =LN(B122/B123) -> -0.045047178 | E122: =LN(C122/C123) -> -0.027844936 | F122: =VLOOKUP(A122,[1]Base!$A$5:$B$265, 2, FALSE) -> 1131.22 | G122: =B122/F122 -> 0.070985308 | H122: =Tabla1[[#This Row],[Merval $]]/F122 -> 2228.582 | I122: =LN(G122/G123) -> -0.032712189 | J122: =LN(H122/H123) -> -0.015509947 | K122: =VLOOKUP(Tabla1[[#This Row],[Fecha]],[1]Base!$N$5:$O$263,2,FALSE) -> 658
A123: 45643 | B123: 84 | C123: =VLOOKUP(Tabla1[[#This Row],[Fecha]],[1]Base!$K$5:$L$249,2,FALSE) -> 2592200.5 | D123: =LN(B123/B124) -> 0.042559614 | E123: =LN(C123/C124) -> 0.019083212 | F123: =VLOOKUP(A123,[1]Base!$A$5:$B$265, 2, FALSE) -> 1145.26 | G123: =B123/F123 -> 0.07334579 | H123: =Tabla1[[#This Row],[Merval $]]/F123 -> 2263.4166 | I123: =LN(G123/G124) -> 0.0024835332 | J123: =LN(H123/H124) -> -0.020992869 | K123: =VLOOKUP(Tabla1[[#This Row],[Fecha]],[1]Base!$N$5:$O$263,2,FALSE) -> 673
A124: 45642 | B124: 80.5 | C124: =VLOOKUP(Tabla1[[#This Row],[Fecha]],[1]Base!$K$5:$L$249,2,FALSE) -> 2543202 | D124: =LN(B124/B125) -> 0.10054123 | E124: =LN(C124/C125) -> 0.070254781 | F124: =VLOOKUP(A124,[1]Base!$A$5:$B$265, 2, FALSE) -> 1100.27 | G124: =B124/F124 -> 0.07316386 | H124: =Tabla1[[#This Row],[Merval $]]/F124 -> 2311.4345 | I124: =LN(G124/G125) -> 0.075518643 | J124: =LN(H124/H125) -> 0.045232195 | K124: =VLOOKUP(Tabla1[[#This Row],[Fecha]],[1]Base!$N$5:$O$263,2,FALSE) -> 677
A125: 45639 | B125: 72.8 | C125: =VLOOKUP(Tabla1[[#This Row],[Fecha]],[1]Base!$K$5:$L$249,2,FALSE) -> 2370661.8 | D125: =LN(B125/B126) -> -0.0027434859 | E125: =LN(C125/C126) -> 0.028483548 | F125: =VLOOKUP(A125,[1]Base!$A$5:$B$265, 2, FALSE) -> 1073.08 | G125: =B125/F125 -> 0.067842099 | H125: =Tabla1[[#This Row],[Merval $]]/F125 -> 2209.2125 | I125: =LN(G125/G126) -> -0.016697703 | J125: =LN(H125/H126) -> 0.014529331 | K125: =VLOOKUP(Tabla1[[#This Row],[Fecha]],[1]Base!$N$5:$O$263,2,FALSE) -> 708
A126: 45638 | B126: 73 | C126: =VLOOKUP(Tabla1[[#This Row],[Fecha]],[1]Base!$K$5:$L$249,2,FALSE) -> 2304089.5 | D126: =LN(B126/B127) -> -0.0041011677 | E126: =LN(C126/C127) -> 0.00563204 | F126: =VLOOKUP(A126,[1]Base!$A$5:$B$265, 2, FALSE) -> 1058.21 | G126: =B126/F126 -> 0.068984417 | H126: =Tabla1[[#This Row],[Merval $]]/F126 -> 2177.3462 | I126: =LN(G126/G127) -> -0.0045643211 | J126: =LN(H126/H127) -> 0.0051688867 | K126: =VLOOKUP(Tabla1[[#This Row],[Fecha]],[1]Base!$N$5:$O$263,2,FALSE) -> 715
... A254: 45450 | B254: 56.1 | C254: =VLOOKUP(Tabla1[[#This Row],[Fecha]],[1]Base!$K$5:$L$249,2,FALSE) -> 1519209.1 | D254: =LN(B254/B255) -> 0.045586744 | E254: =LN(C254/C255) -> 0.010242279 | F254: =VLOOKUP(A254,[1]Base!$A$5:$B$265, 2, FALSE) -> 1282.33 | G254: =B254/F254 -> 0.043748489 | H254: =Tabla1[[#This Row],[Merval $]]/F254 -> 1184.7256 | I254: =LN(G254/G255) -> 0.037506335 | J254: =LN(H254/H255) -> 0.0021618703 | K254: =VLOOKUP(Tabla1[[#This Row],[Fecha]],[1]Base!$N$5:$O$263,2,FALSE) -> 1582
A255: 45449 | B255: 53.6 | C255: =VLOOKUP(Tabla1[[#This Row],[Fecha]],[1]Base!$K$5:$L$249,2,FALSE) -> 1503728.4 | F255: =VLOOKUP(A255,[1]Base!$A$5:$B$265, 2, FALSE) -> 1272.01 | G255: =B255/F255 -> 0.042138034 | H255: =Tabla1[[#This Row],[Merval $]]/F255 -> 1182.1671 | K255: =VLOOKUP(Tabla1[[#This Row],[Fecha]],[1]Base!$N$5:$O$263,2,FALSE) -> 1596

Sheet 2) Research
K22: Facturacion | N22: Precio promedio 2024 | O22: 112183500
K23: Mercado | L23: 773617700000 | N23: Precio Agrometal | O23: ='6) Proyecciones'!F15 -> 1.9967982e+08
K24: AGRO | L24: 84924515513 | N24: Sobre precio | O24: =O23/O22 -> 1.7799393
K25: Participación | L25: =L24/L23 -> 0.10977582
K28: Empresa | L28: Producción agrícola | M28: Participación
K29: Mercado | L29: 6896
K30: John Deere | L30: 1634.352 | M30: =L30/$L$29 -> 0.237
K31: New Holland | L31: 724.08 | M31: =L31/$L$29 -> 0.105
K32: Case IH | L32: 799.936 | M32: =L32/$L$29 -> 0.116
K33: Crucianelli | L33: 393.072 | M33: =L33/$L$29 -> 0.057
K34: Pauny | L34: 413.76 | M34: =L34/$L$29 -> 0.06
K35: Metlflor | L35: 234.464 | M35: =L35/$L$29 -> 0.034
K36: Agrometal | L36: 323 | M36: =L36/$L$29 -> 0.046838747
K37: Pla | L37: 199.984 | M37: =L37/$L$29 -> 0.029
K38: Massey Ferguson | L38: 199.984 | M38: =L38/$L$29 -> 0.029
K39: Mainero | L39: 179.296 | M39: =L39/$L$29 -> 0.026
K41: Fuente: elaboración propia en base a RNM e INDEC

Sheet 3) Macro
B6: IPC mensual base 2016 | C6: Inflación mensual | D6: TC MEP | E6: EMAE base 2004 | F6: M/M% | H6: Columna1 | I6: Inflación anual | J6: TC MEP | K6: PBI
A7: 43831 | B7: 289.8299 | E7: 140.70852 | H7: 2020 | I7: =[1]Base!V16 -> 0.361 | J7: 122.63622 | K7: =Base!$AJ14 -> -0.099
A8: 43862 | B8: 295.666 | C8: =B8/B7-1 -> 0.020136294 | E8: 138.88807 | F8: =E8/E7-1 -> -0.012937698 | H8: 2021 | I8: =[1]Base!V28 -> 0.50941634 | J8: 164.48068 | K8: =Base!$AJ15 -> 0.10441812
A9: 43891 | B9: 305.5515 | C9: =B9/B8-1 -> 0.033434686 | D9: 87.930833 | E9: 125.48317 | F9: =E9/E8-1 -> -0.096515867 | H9: 2022 | I9: =[1]Base!V40 -> 0.94793182 | J9: 250.58223 | K9: =Base!$AJ16 -> 0.052698797
A10: 43922 | B10: 310.1243 | C10: =B10/B9-1 -> 0.014965726 | D10: 100.62767 | E10: 106.10837 | F10: =E10/E9-1 -> -0.15440158 | H10: 2023 | I10: =[1]Base!V52 -> 2.1140764 | J10: 573.54615 | K10: =Base!$AJ17 -> -0.016110016
A11: 43952 | B11: 314.9087 | C11: =B11/B10-1 -> 0.015427363 | D11: 113.14742 | E11: 117.63514 | F11: =E11/E10-1 -> 0.10863201 | H11: 2024 | I11: =[1]Base!V64 -> 1.1776363 | J11: 1163.4084 | K11: =Base!$AJ18 -> -0.017191052
A12: 43983 | B12: 321.9738 | C12: =B12/B11-1 -> 0.022435392 | D12: 106.66552 | E12: 124.84622 | F12: =E12/E11-1 -> 0.061300389 | H12: 2025 | I12: 0.359 | J12: 1300 | K12: =Base!$AJ19 -> 0.055
A13: 44013 | B13: 328.2014 | C13: =B13/B12-1 -> 0.019341946 | D13: 112.09 | E13: 126.19018 | F13: =E13/E12-1 -> 0.010764958 | H13: 2026E | I13: 0.145 | J13: ='6) Proyecciones'!H7 -> 1715.4565 | K13: =Base!$AJ20 -> 0.045
A14: 44044 | B14: 337.0632 | C14: =B14/B13-1 -> 0.027001104 | D14: 124.42871 | E14: 129.01079 | F14: =E14/E13-1 -> 0.022352027 | H14: 2027E | I14: 0.094 | J14: ='6) Proyecciones'!I7 -> 1838.6132 | K14: =Base!$AJ21 -> 0.04
A15: 44075 | B15: 346.6207 | C15: =B15/B14-1 -> 0.028355216 | D15: 126.99267 | E15: 130.82176 | F15: =E15/E14-1 -> 0.014037415 | H15: 2028E | I15: 0.075 | J15: ='6) Proyecciones'!J7 -> 1933.0625 | K15: =Base!$AJ22 -> 0.032
A16: 44105 | B16: 359.657 | C16: =B16/B15-1 -> 0.037609698 | D16: 147.92129 | E16: 133.64962 | F16: =E16/E15-1 -> 0.021616074 | H16: 2029E | I16: 0.075 | J16: ='6) Proyecciones'!K7 -> 2033.3094 | K16: =Base!$AJ23 -> 0.031
A17: 44136 | B17: 371.0211 | C17: =B17/B16-1 -> 0.031597049 | D17: 143.776 | E17: 134.91069 | F17: =E17/E16-1 -> 0.0094356794 | H17: 2030E | I17: 0.075 | J17: ='6) Proyecciones'!L7 -> 2138.7549 | K17: =Base!$AJ24 -> 0.03
A18: 44166 | B18: 385.8826 | C18: =B18/B17-1 -> 0.040055673 | D18: 140.59323 | E18: 136.76102 | F18: =E18/E17-1 -> 0.013715173
A19: 44197 | B19: 401.5071 | C19: =B19/B18-1 -> 0.040490294 | D19: 145.18355 | E19: 139.73714 | F19: =E19/E18-1 -> 0.021761532
A20: 44228 | B20: 415.8595 | C20: =B20/B19-1 -> 0.035746317 | D20: 145.555 | E20: 137.25835 | F20: =E20/E19-1 -> -0.017739016
A21: 44256 | B21: 435.8657 | C21: =B21/B20-1 -> 0.048108075 | D21: 143.5729 | E21: 140.61116 | F21: =E21/E20-1 -> 0.024427004
A22: 44287 | B22: 453.6503 | C22: =B22/B21-1 -> 0.040802935 | D22: 145.49033 | E22: 139.63372 | F22: =E22/E21-1 -> -0.0069513487
A23: 44317 | B23: 468.725 | C23: =B23/B22-1 -> 0.033229781 | D23: 155.76968 | E23: 139.10437 | F23: =E23/E22-1 -> -0.0037910015
A24: 44348 | B24: 483.6049 | C24: =B24/B23-1 -> 0.03174548 | D24: 160.68433 | E24: 141.74208 | F24: =E24/E23-1 -> 0.018962146
A25: 44378 | B25: 498.0987 | C25: =B25/B24-1 -> 0.029970333 | D25: 166.38548 | E25: 141.54961 | F25: =E25/E24-1 -> -0.0013579115
A26: 44409 | B26: 510.3942 | C26: =B26/B25-1 -> 0.024684867 | D26: 169.62581 | E26: 143.43631 | F26: =E26/E25-1 -> 0.013328855
A27: 44440 | B27: 528.4968 | C27: =B27/B26-1 -> 0.03546788 | D27: 172.06467 | E27: 144.04418 | F27: =E27/E26-1 -> 0.0042379518
A28: 44470 | B28: 547.0802 | C28: =B28/B27-1 -> 0.035162748 | D28: 177.66645 | E28: 143.53112 | F28: =E28/E27-1 -> -0.003561816
A29: 44501 | B29: 560.9184 | C29: =B29/B28-1 -> 0.025294646 | D29: 192.11067 | E29: 145.86834 | F29: =E29/E28-1 -> 0.016283706
... A56: 45323 | B56: 4825.7881 | C56: =B56/B55-1 -> 0.13240676 | D56: 1124.1981 | E56: 142.72178 | F56: =E56/E55-1 -> -0.0036641006
A57: 45352 | B57: 5357.0929 | C57: =B57/B56-1 -> 0.110097 | D57: 1019.4886 | E57: 141.63784 | F57: =E57/E56-1 -> -0.0075948112 | G57: EMAE interanual
A58: 45383 | B58: 5830.2271 | C58: =B58/B57-1 -> 0.088319208 | D58: 1014.2714 | E58: 139.89994 | F58: =E58/E57-1 -> -0.012269973 | G58: =E58/$E$57-1 -> -0.012269973
A59: 45413 | B59: 6073.7165 | C59: =B59/B58-1 -> 0.041763279 | D59: 1114.0826 | E59: 141.22741 | F59: =E59/E58-1 -> 0.0094886652 | G59: =E59/$E$57-1 -> -0.0028977335
A60: 45444 | B60: 6351.7145 | C60: =B60/B59-1 -> 0.045770658 | D60: 1281.3585 | E60: 141.59164 | F60: =E60/E59-1 -> 0.0025790429 | G60: =E60/$E$57-1 -> -0.00032616397
A61: 45474 | B61: 6607.7479 | C61: =B61/B60-1 -> 0.040309337 | D61: 1349.1143 | E61: 145.52645 | F61: =E61/E60-1 -> 0.027789836 | G61: =E61/$E$57-1 -> 0.027454608
A62: 45505 | B62: 6883.4412 | C62: =B62/B61-1 -> 0.041722733 | D62: 1295.3645 | E62: 146.97579 | F62: =E62/E61-1 -> 0.0099592976 | G62: =E62/$E$57-1 -> 0.037687335
A63: 45536 | B63: 7122.2421 | C63: =B63/B62-1 -> 0.034692081 | D63: 1228.551 | E63: 146.96724 | F63: =E63/E62-1 -> -5.8181092e-05 | G63: =E63/$E$57-1 -> 0.037626961
A64: 45566 | B64: 7313.9542 | C64: =B64/B63-1 -> 0.02691738 | D64: 1159.8122 | E64: 147.57859 | F64: =E64/E63-1 -> 0.0041597753 | G64: =E64/$E$57-1 -> 0.041943256
A65: 45597 | B65: 7491.4314 | C65: =B65/B64-1 -> 0.024265561 | D65: 1106.0081 | E65: 148.88807 | F65: =E65/E64-1 -> 0.0088731002 | G65: =E65/$E$57-1 -> 0.051188523
A66: 45627 | B66: 7694.0075 | C66: =B66/B65-1 -> 0.027041041 | D66: 1111.2664 | E66: 150.68166 | F66: =E66/E65-1 -> 0.01204659 | G66: =E66/$E$57-1 -> 0.06385176
A67: 45658 | B67: 7864.1257 | C67: =B67/B66-1 -> 0.02211048 | D67: 1164.7291 | E67: 151.46936 | F67: =E67/E66-1 -> 0.0052275413 | G67: =E67/$E$57-1 -> 0.069413089
A68: 45689 | B68: 8052.9927 | C68: =B68/B67-1 -> 0.024016274 | D68: 1198.356 | E68: 152.59215 | F68: =E68/E67-1 -> 0.0074126791 | G68: =E68/$E$57-1 -> 0.077340306
A69: 45717 | B69: 8353.3158 | C69: =B69/B68-1 -> 0.037293353 | D69: 1262.3324 | E69: 149.89801 | F69: =E69/E68-1 -> -0.017655814 | G69: =E69/$E$57-1 -> 0.058318986
A70: 45748 | B70: 8585.6078 | C70: =B70/B69-1 -> 0.027808358 | D70: 1245.3718 | F70: =E70/E69-1 -> -1
A71: 45778 | D71: 1159.7591 | F71: =E71/E70-1 -> #DIV/0!
A72: 45809 | D72: 1190.29 | F72: =E72/E71-1 -> #DIV/0!

Sheet 4) Financial Statements
A1: FINANCIAL STATEMENTS | B1: 2020 | C1: 2021 | D1: 2022 | E1: 2023 | F1: 2024
A2: Dólar Promedio | B2: ='3) Macro'!J7 -> 122.63622 | C2: ='3) Macro'!J8 -> 164.48068 | D2: ='3) Macro'!J9 -> 250.58223 | E2: ='3) Macro'!J10 -> 573.54615 | F2: ='3) Macro'!J11 -> 1163.4084
A5: PESOS ($)
A6: Income Statement
A7: Revenues | B7: 3640221476 | C7: 7933240381 | D7: 14658891753 | E7: 22474661058 | F7: 63697863191
A8: Operating Costs | B8: =-2236831045 -> -2236831045 | C8: =-4721883737 -> -4721883737 | D8: =-8678223967 -> -8678223967 | E8: =-15735402981 -> -15735402981 | F8: =-44705660747 -> -44705660747
A9: Gross Income | B9: =B7+B8 -> 1403390431 | C9: =C7+C8 -> 3211356644 | D9: =D7+D8 -> 5980667786 | E9: =E7+E8 -> 6739258077 | F9: =F7+F8 -> 18992202444
A10: SG&A | B10: =-SUM(B11:B12) -> -386635412 | C10: =-SUM(C11:C12) -> -754386815 | D10: =-SUM(D11:D12) -> -1621608974 | E10: =-SUM(E11:E12) -> -4189118364 | F10: =-SUM(F11:F12) -> -9936762045
A11: Gasto de comercialización | B11: =183116829 -> 183116829 | C11: 358109025 | D11: =796614304 -> 796614304 | E11: =1824457306 -> 1824457306 | F11: 4852573989
A12: Gasto de administración | B12: 203518583 | C12: 396277790 | D12: =824994670 -> 824994670 | E12: =2364661058 -> 2364661058 | F12: 5084188056
A13: Others | B13: =SUM(B14:B15) -> -183984112 | C13: =SUM(C14:C15) -> -516085800 | D13: =SUM(D14:D15) -> -2491222223 | E13: =SUM(E14:E15) -> -4189674224 | F13: =SUM(F14:F15) -> -3049579706
A14: Resultado por exposición a los cambios en el poder adquisitivo de la moneda | B14: =-110905318 -> -110905318 | C14: =-524480520 -> -524480520 | D14: =-2505563439 -> -2505563439 | E14: =-4282932805 -> -4282932805 | F14: =-3060635304 -> -3060635304
A15: Ingresos y egresos netos | B15: =-73078794 -> -73078794 | C15: 8394720 | D15: =14341216 -> 14341216 | E15: 93258581 | F15: 11055598
A16: EBIT | B16: =B9+B10+B13 -> 832770907 | C16: =C9+C10+C13 -> 1940884029 | D16: =D9+D10+D13 -> 1867836589 | E16: =E9+E10+E13 -> -1639534511 | F16: =F9+F10+F13 -> 6005860693
A17: Net Financial Results | B17: =SUM(B18:B19) -> -387280955 | C17: =SUM(C18:C19) -> -201465816 | D17: =SUM(D18:D19) -> -496556473 | E17: =SUM(E18:E19) -> -2213503083 | F17: =SUM(F18:F19) -> -295881714
A18: Ingresos financieros | B18: 85862010 | C18: 300420734 | D18: =725355208 -> 725355208 | E18: 2567148681 | F18: 2678678603
A19: Egresos financieros | B19: =-473142965 -> -473142965 | C19: =-501886550 -> -501886550 | D19: =-1221911681 -> -1221911681 | E19: =-4780651764 -> -4780651764 | F19: =-2974560317 -> -2974560317
A20: Earnings Before Taxes | B20: =B16+B17 -> 445489952 | C20: =C16+C17 -> 1739418213 | D20: =D16+D17 -> 1371280116 | E20: =E16+E17 -> -3853037594 | F20: =F16+F17 -> 5709978979
A21: Income Tax | B21: =-143150963 -> -143150963 | C21: =-619392065 -> -619392065 | D21: =-535054471 -> -535054471 | E21: 615553017 | F21: =-3125369576 -> -3125369576
A22: Net Income | B22: =B20+B21 -> 302338989 | C22: =C20+C21 -> 1120026148 | D22: =D20+D21 -> 836225645 | E22: =E20+E21 -> -3237484577 | F22: =F20+F21 -> 2584609403
B24: =B21/B20 -> -0.32133376 | C24: =C21/C20 -> -0.35609151 | D24: =D21/D20 -> -0.39018612 | E24: =E21/E20 -> -0.15975785 | F24: =F21/F20 -> -0.5473522 | G24: =AVERAGE(B24:F24) -> -0.35494429
A25: Balance Sheet
A26: Cash & ST Investments | B26: 588858045 | C26: 1186625716 | D26: 1275948509 | E26: 2458458439 | F26: 7394531088
A27: Receivables | B27: 343644441 | C27: 1013004174 | D27: 1459736354 | E27: 3182055900 | F27: 12851298972
A28: Inventories | B28: 443240255 | C28: 1119818347 | D28: 1890044461 | E28: 4084702777 | F28: 8678279963
A29: Other receivables | B29: 644764271 | C29: 1507979735 | D29: 1839629040 | E29: 2447289605 | F29: 3892334361
A30: Current Assets | B30: =SUM(B26:B29) -> 2020507012 | C30: =SUM(C26:C29) -> 4827427972 | D30: =SUM(D26:D29) -> 6465358364 | E30: =SUM(E26:E29) -> 12172506721 | F30: =SUM(F26:F29) -> 32816444384
A31: Fixed Assets | B31: 757842389 | C31: 1203471344 | D31: 2684795381 | E31: 8428778720 | F31: 18385420430
A32: Other | B32: =SUM(B33:B35) -> 8497777 | C32: =SUM(C33:C35) -> 12538187 | D32: =SUM(D33:D35) -> 23869289 | E32: =SUM(E33:E35) -> 592415966 | F32: =SUM(F33:F35) -> 3261326089
A33: Propiedades de inversión | B33: 8497777 | C33: 12538187 | D33: 23869289 | E33: 72600386 | F33: 154358791
A34: Activo por impuesto diferido | C34: 0 | D34: 0 | E34: 519815580 | F34: 31162108
A35: Créditos por ventas | C35: 0 | D35: 0 | E35: 0 | F35: 3075805190
A36: Non Current Assets | B36: =SUM(B31:B32) -> 766340166 | C36: =SUM(C31:C32) -> 1216009531 | D36: =SUM(D31:D32) -> 2708664670 | E36: =SUM(E31:E32) -> 9021194686 | F36: =SUM(F31:F32) -> 21646746519
A37: Total Assets | B37: =B30+B36 -> 2786847178 | C37: =C30+C36 -> 6043437503 | D37: =D30+D36 -> 9174023034 | E37: =E30+E36 -> 21193701407 | F37: =F30+F36 -> 54463190903
A38: Payables | B38: 378394206 | C38: 421151305 | D38: 914425611 | E38: 663133450 | F38: 5442752288
A39: Loans | B39: 293554093 | C39: 482245050 | D39: 1031754217 | E39: 3665556676 | F39: 6886952651
A40: Remuneraciones y Deudas sociales | B40: 74744081 | C40: 179220183 | D40: 296617720 | E40: 581546869 | F40: 1280599720
A41: Fiscales | B41: 127303502 | C41: 635763012 | D41: 113803295 | E41: 88779717 | F41: 2924936225
A42: Anticipos de Clientes | B42: 514650909 | C42: 1204710440 | D42: 675522485 | E42: 950830550 | F42: 3092212223
A43: Other | B43: 36471143 | C43: 97000000 | D43: 216684944 | E43: 681524392 | F43: 1386572832
A44: Current Liabilities | B44: =SUM(B38:B43) -> 1425117934 | C44: =SUM(C38:C43) -> 3020089990 | D44: =SUM(D38:D43) -> 3248808272 | E44: =SUM(E38:E43) -> 6631371654 | F44: =SUM(F38:F43) -> 21014025939
A45: Loans | B45: 85161167 | C45: 83869806 | D45: 269771457 | E45: 853382678 | F45: 1218164492
A46: Fiscales | B46: 47897880 | C46: 37313435 | D46: 22766168 | E46: 10909775 | F46: 29410
A47: Sociales | B47: 22498759 | C47: 16095197 | D47: 9826826 | E47: 3733110 | F47: 0
A48: Other | B48: =SUM(B49:B50) -> 65123505 | C48: =SUM(C49:C50) -> 60793535 | D48: =D50 -> 151787104 | E48: =E50 -> 0 | F48: 500
A49: Otras | B49: 500 | C49: 500 | E49: 500
A50: Pasivo por impuesto diferidos | B50: 65123005 | C50: 60793035 | D50: 151787104
A51: Non Current Liabilities | B51: =SUM(B45:B48) -> 220681311 | C51: =SUM(C45:C48) -> 198071973 | D51: =SUM(D45:D48) -> 454151555 | E51: =SUM(E45:E49) -> 868026063 | F51: =SUM(F45:F48) -> 1218194402
A52: Total Liabilities | B52: =B44+B51 -> 1645799245 | C52: =C44+C51 -> 3218161963 | D52: =D44+D51 -> 3702959827 | E52: =E44+E51 -> 7499397717 | F52: =F44+F51 -> 22232220341
A53: Patrimonio Neto | B53: =B37-B52 -> 1141047933 | C53: =C37-C52 -> 2825275540 | D53: =D37-D52 -> 5471063207 | E53: =E37-E52 -> 13694303690 | F53: =F37-F52 -> 32230970562
A56: Cash Flow
A57: Ganancia/pérdida del ejercicio | B57: 280568734 | C57: 1103434209 | D57: 806426455 | E57: =-3342587137 -> -3342587137 | F57: 2404777126
A58: Más/menos impuestos a las ganancias | B58: 143150963 | C58: 619392065 | D58: 535054471 | E58: =-615553017 -> -615553017 | F58: =3125369576 -> 3125369576
A59: Ajustes provenientes de act operativas | B59: =B58+B60+B63+B64+B65+B66 -> 363314444 | C59: =C58+C60+C63+C64+C65+C66 -> 1027954489 | D59: =D58+D60+D63+D64+D65+D66 -> 1418497232 | E59: =E58+E60+E63+E64+E65+E66 -> 2827710262 | F59: =F58+F60+F63+F64+F65+F66 -> 8307137141
A60: D&A | B60: =B61+B62 -> 53264938 | C60: =C61+C62 -> 99225981 | D60: =D61+D62 -> 222987557 | E60: =E61+E62 -> 745065494 | F60: =F61+F62 -> 1531948674
A61: Depreciación de propiedades, planta y equipo | B61: 53076099 | C61: 98941022 | D61: 222432457 | E61: 743336913 | F61: 1528183825
A62: Depreciación de propiedades de inversión | B62: 188839 | C62: 284959 | D62: 555100 | E62: 1728581 | F62: 3764849
A63: Provisiones comerciales y sociales | B63: 83737797 | C63: 166905365 | D63: 321961471 | E63: 1078883106 | F63: 2151071359
A64: Provisión de honorarios al directorio | B64: 35000000 | C64: 97000000 | D64: 200000000 | E64: 600000000 | F64: 1200000000
A65: Provisión deterioro de valor créditos | B65: =-3831345 -> -3831345 | C65: =-880012 -> -880012 | D65: 1569729 | E65: 6478021 | F65: 41884111
A66: Diferencia de conversión de deudas | B66: 51992091 | C66: 46311090 | D66: 136924004 | E66: 1012836658 | F66: 256863421
A67: Working Capital | B67: =SUM(B68:B75) -> 86965203 | C67: =SUM(C68:C75) -> -1622844010 | D67: =SUM(D68:D75) -> -1920466344 | E67: =SUM(E68:E75) -> 358542729 | F67: =SUM(F68:F75) -> -5122185265
A68: Variación de deudas comerciales | B68: 20585622 | C68: =-164344519 -> -164344519 | D68: 69466106 | E68: =-2187394862 -> -2187394862 | F68: 3798913682
A69: Disminución de deudas sociales | B69: =-39790005 -> -39790005 | C69: =-20506369 -> -20506369 | D69: =-195808249 -> -195808249 | E69: =-1270266381 -> -1270266381 | F69: =-1910247926 -> -1910247926
A70: Disminución de deudas fiscales | B70: =-12803717 -> -12803717 | C70: =-261494767 -> -261494767 | D70: =-1676275654 -> -1676275654 | E70: =-182699841 -> -182699841 | F70: =-417527655 -> -417527655
A71: Disminución de otras deudas | B71: =-22071938 -> -22071938 | C71: =-55035210 -> -55035210 | D71: =-172272030 -> -172272030 | E71: =-593232024 -> -593232024 | F71: =-1297787883 -> -1297787883
A72: Variación de anticipo a clientes | B72: =447737431 -> 447737431 | C72: 428102217 | D72: =-1671253454 -> -1671253454 | E72: =-1152746468 -> -1152746468 | F72: 1021303286
A73: Variación de créditos por ventas | B73: =-67159671 -> -67159671 | C73: =-563566112 -> -563566112 | D73: 336399775 | E73: 1182486981 | F73: =-5998094889 -> -5998094889
A74: Variación de otros créditos | B74: =-214598597 -> -214598597 | C74: =-535030448 -> -535030448 | D74: 1097915483 | E74: 2761499649 | F74: =-536946565 -> -536946565
A75: Variación de bienes de cambio | B75: =-24933922 -> -24933922 | C75: =-450968802 -> -450968802 | D75: 291361679 | E75: 1800895675 | F75: 218202685
A76: Other | B76: 0 | C76: 0
A77: Cash Flow from Operating Activities (CFO) | B77: =B67+B59+B57 -> 730848381 | C77: =C67+C59+C57 -> 508544688 | D77: =D67+D59+D57 -> 304457343 | E77: =E67+E59+E57 -> -156334146 | F77: =F67+F59+F57 -> 5589729002
A78: CAPEX | B78: =-42183587 -> -42183587 | C78: =-158828201 -> -158828201 | D78: =-562865660 -> -562865660 | E78: =-811662819 -> -811662819 | F78: =-1555724203 -> -1555724203
A79: Other | B79: 0 | C79: 0 | D79: 0 | E79: 0 | F79: 0
A80: Cash Flow from Investing Activities (CFI) | B80: =SUM(B78:B79) -> -42183587 | C80: =SUM(C78:C79) -> -158828201 | D80: =SUM(D78:D79) -> -562865660 | E80: =SUM(E78:E79) -> -811662819 | F80: =SUM(F78:F79) -> -1555724203
A81: Debt | B81: =-188002745 -> -188002745 | C81: =-51677561 -> -51677561 | D81: 61809931 | E81: =-546848253 -> -546848253 | F81: =-1993996191 -> -1993996191
A82: Dividends | B82: 0 | C82: 0 | D82: =-839000000 -> -839000000 | E82: 0 | F82: 0
A83: Other | B83: 0 | C83: 0 | D83: 0 | E83: 0 | F83: 0
A84: Cash Flow from Financing Activities (CFF) | B84: =SUM(B81:B83) -> -188002745 | C84: =SUM(C81:C83) -> -51677561 | D84: =SUM(D81:D83) -> -777190069 | E84: =SUM(E81:E83) -> -546848253 | F84: =SUM(F81:F83) -> -1993996191
A85: Net Changes in Cash | B85: =B77+B80+B84 -> 500662049 | C85: =C77+C80+C84 -> 298038926 | D85: =D77+D80+D84 -> -1035598386 | E85: =E77+E80+E84 -> -1514845218 | F85: =F77+F80+F84 -> 2040008608
A88: Dólares (US$)
A89: Income Statement | B89: 2020 | C89: 2021 | D89: 2022 | E89: 2023 | F89: 2024
A90: Revenues | B90: =B7/B$2 -> 29683085 | C90: =C7/C$2 -> 48232049 | D90: =D7/D$2 -> 58499326 | E90: =E7/E$2 -> 39185445 | F90: =F7/F$2 -> 54751076
A91: Operating Costs | B91: =B8/B$2 -> -18239562 | C91: =C8/C$2 -> -28707831 | D91: =D8/D$2 -> -34632240 | E91: =E8/E$2 -> -27435286 | F91: =F8/F$2 -> -38426454
A92: Gross Income | B92: =B9/B$2 -> 11443523 | C92: =C9/C$2 -> 19524217 | D92: =D9/D$2 -> 23867086 | E92: =E9/E$2 -> 11750158 | F92: =F9/F$2 -> 16324622
A93: SG&A | B93: =B10/B$2 -> -3152701.5 | C93: =C10/C$2 -> -4586476.6 | D93: =D10/D$2 -> -6471364.5 | E93: =E10/E$2 -> -7303890.6 | F93: =F10/F$2 -> -8541077.9
A94: Others | B94: =B13/B$2 -> -1500242.8 | C94: =C13/C$2 -> -3137668.1 | D94: =D13/D$2 -> -9941735.2 | E94: =E13/E$2 -> -7304859.8 | F94: =F13/F$2 -> -2621246
A95: EBIT | B95: =B16/B$2 -> 6790578.5 | C95: =C16/C$2 -> 11800073 | D95: =D16/D$2 -> 7453986.5 | E95: =E16/E$2 -> -2858592.1 | F95: =F16/F$2 -> 5162297.7
A96: Net Financial Results | B96: =B17/B$2 -> -3157965.4 | C96: =C17/C$2 -> -1224860 | D96: =D17/D$2 -> -1981610.8 | E96: =E17/E$2 -> -3859328.6 | F96: =F17/F$2 -> -254323.16
A97: Earnings Before Taxes | B97: =B20/B$2 -> 3632613.1 | C97: =C20/C$2 -> 10575213 | D97: =D20/D$2 -> 5472375.7 | E97: =E20/E$2 -> -6717920.7 | F97: =F20/F$2 -> 4907974.5
A98: Income Tax | B98: =B21/B$2 -> -1167281.2 | C98: =C21/C$2 -> -3765743.5 | D98: =D21/D$2 -> -2135245 | E98: =E21/E$2 -> 1073240.6 | F98: =F21/F$2 -> -2686390.7
A99: Net Income | B99: =B22/B$2 -> 2465331.9 | C99: =C22/C$2 -> 6809469.1 | D99: =D22/D$2 -> 3337130.6 | E99: =E22/E$2 -> -5644680.1 | F99: =F22/F$2 -> 2221583.9
A100: Operating Costs | B100: =B91*-1 -> 18239562 | C100: =C91*-1 -> 28707831 | D100: =D91*-1 -> 34632240 | E100: =E91*-1 -> 27435286 | F100: =F91*-1 -> 38426454
A102: Balance Sheet | B102: 2020 | C102: 2021 | D102: 2022 | E102: 2023 | F102: 2024 | I102: 2020 | J102: 2021 | K102: 2022 | L102: 2023 | M102: 2024
A103: Cash & ST Investments | B103: =B26/B$2 -> 4801664.8 | C103: =C26/C$2 -> 7214377.3 | D103: =D26/D$2 -> 5091935.3 | E103: =E26/E$2 -> 4286417.8 | F103: =F26/F$2 -> 6355920.1 | G103: =F103/B103-1 -> 0.32369091 | H103: Cash & ST Investments | I103: =B103/B$107 -> 0.29144073 | J103: =C103/C$107 -> 0.2458091 | K103: =D103/D$107 -> 0.19735155 | L103: =E103/E$107 -> 0.20196813 | M103: =F103/F$107 -> 0.22533005
A104: Receivables | B104: =B27/B$2 -> 2802144.7 | C104: =C27/C$2 -> 6158803.2 | D104: =D27/D$2 -> 5825378.5 | E104: =E27/E$2 -> 5548038.1 | F104: =F27/F$2 -> 11046249 | G104: =F104/B104-1 -> 2.9420694 | H104: Receivables | I104: =B104/B$107 -> 0.17007832 | J104: =C104/C$107 -> 0.20984346 | K104: =D104/D$107 -> 0.2257781 | L104: =E104/E$107 -> 0.26141336 | M104: =F104/F$107 -> 0.39161156
A105: Inventories | B105: =B28/B$2 -> 3614268.6 | C105: =C28/C$2 -> 6808205.8 | D105: =D28/D$2 -> 7542611.6 | E105: =E28/E$2 -> 7121838 | F105: =F28/F$2 -> 7459358 | G105: =F105/B105-1 -> 1.0638637 | H105: Inventories | I105: =B105/B$107 -> 0.21937081 | J105: =C105/C$107 -> 0.23196998 | K105: =D105/D$107 -> 0.29233406 | L105: =E105/E$107 -> 0.33556792 | M105: =F105/F$107 -> 0.26444912
A106: Other receivables | B106: =B29/B$2 -> 5257535.3 | C106: =C29/C$2 -> 9168126.6 | D106: =D29/D$2 -> 7341418.5 | E106: =E29/E$2 -> 4266944.5 | F106: =F29/F$2 -> 3345630.2 | G106: =F106/B106-1 -> -0.36365046 | H106: Other receivables | I106: =B106/B$107 -> 0.31911014 | J106: =C106/C$107 -> 0.31237747 | K106: =D106/D$107 -> 0.28453628 | L106: =E106/E$107 -> 0.20105059 | M106: =F106/F$107 -> 0.11860927
A107: Current Assets | B107: =B30/B$2 -> 16475613 | C107: =C30/C$2 -> 29349513 | D107: =D30/D$2 -> 25801344 | E107: =E30/E$2 -> 21223238 | F107: =F30/F$2 -> 28207157 | G107: =F107/B107-1 -> 0.71205504 | H107: Current Assets | I107: =B107/B111 -> 0.72501536 | J107: =C107/C111 -> 0.79878843 | K107: =D107/D111 -> 0.70474625 | L107: =E107/E111 -> 0.57434549 | M107: =F107/F111 -> 0.60254355 | N107: Respecto al total
A108: Fixed Assets | B108: =B31/B$2 -> 6179596.6 | C108: =C31/C$2 -> 7316794.3 | D108: =D31/D$2 -> 10714229 | E108: =E31/E$2 -> 14695903 | F108: =F31/F$2 -> 15803066 | G108: =F108/B108-1 -> 1.5572974 | H108: Fixed Assets | I108: =B108/B$110 -> 0.98891122 | J108: =C108/C$110 -> 0.98968907 | K108: =D108/D$110 -> 0.9911878 | L108: =E108/E$110 -> 0.93433065 | M108: =F108/F$110 -> 0.84933874
...

Sheet 5) Ratios
A5: Indicador | B5: 2020 | C5: 2021 | D5: 2022 | E5: 2023 | F5: 2024
A6: Ratios de liquidez
A7: Liquidez corriente | B7: ='4) Financial Statements'!B$30/'4) Financial Statements'!B$44 -> 1.4177823 | C7: ='4) Financial Statements'!C$30/'4) Financial Statements'!C$44 -> 1.5984385 | D7: ='4) Financial Statements'!D$30/'4) Financial Statements'!D$44 -> 1.9900708 | E7: ='4) Financial Statements'!E$30/'4) Financial Statements'!E$44 -> 1.8355941 | F7: ='4) Financial Statements'!F$30/'4) Financial Statements'!F$44 -> 1.5616448
A8: Liquidez seca | B8: =('4) Financial Statements'!B$30-'4) Financial Statements'!B$28)/'4) Financial Statements'!B$44 -> 1.1067623 | C8: =('4) Financial Statements'!C$30-'4) Financial Statements'!C$28)/'4) Financial Statements'!C$44 -> 1.2276487 | D8: =('4) Financial Statements'!D$30-'4) Financial Statements'!D$28)/'4) Financial Statements'!D$44 -> 1.4083053 | E8: =('4) Financial Statements'!E$30-'4) Financial Statements'!E$28)/'4) Financial Statements'!E$44 -> 1.2196276 | F8: =('4) Financial Statements'!F$30-'4) Financial Statements'!F$28)/'4) Financial Statements'!F$44 -> 1.1486692
A9: Liquidez de CP | B9: =('4) Financial Statements'!B$26+'4) Financial Statements'!B$27)/'4) Financial Statements'!B$44 -> 0.65433356 | C9: =('4) Financial Statements'!C$26+'4) Financial Statements'!C$27)/'4) Financial Statements'!C$44 -> 0.72833257 | D9: =('4) Financial Statements'!D$26+'4) Financial Statements'!D$27)/'4) Financial Statements'!D$44 -> 0.84205796 | E9: =('4) Financial Statements'!E$26+'4) Financial Statements'!E$27)/'4) Financial Statements'!E$44 -> 0.85058034 | F9: =('4) Financial Statements'!F$26+'4) Financial Statements'!F$27)/'4) Financial Statements'!F$44 -> 0.96344366
A10: Capital de Trabajo | B10: ='4) Financial Statements'!B$107-'4) Financial Statements'!B$115 -> 4854920.2 | C10: ='4) Financial Statements'!C$107-'4) Financial Statements'!C$115 -> 10988147 | D10: ='4) Financial Statements'!D$107-'4) Financial Statements'!D$115 -> 12836305 | E10: ='4) Financial Statements'!E$107-'4) Financial Statements'!E$115 -> 9661184.2 | F10: ='4) Financial Statements'!F$107-'4) Financial Statements'!F$115 -> 10144690
A11: Liquidez operativa | B11: =(('4) Financial Statements'!B53+('4) Financial Statements'!B39+'4) Financial Statements'!B45-'4) Financial Statements'!B26))/'4) Financial Statements'!B37) -> 0.33403523 | C11: =(('4) Financial Statements'!C53+('4) Financial Statements'!C39+'4) Financial Statements'!C45-'4) Financial Statements'!C26))/'4) Financial Statements'!C37) -> 0.36481964 | D11: =(('4) Financial Statements'!D53+('4) Financial Statements'!D39+'4) Financial Statements'!D45-'4) Financial Statements'!D26))/'4) Financial Statements'!D37) -> 0.59915267 | E11: =(('4) Financial Statements'!E53+('4) Financial Statements'!E39+'4) Financial Statements'!E45-'4) Financial Statements'!E26))/'4) Financial Statements'!E37) -> 0.74337108 | F11: =(('4) Financial Statements'!F53+('4) Financial Statements'!F39+'4) Financial Statements'!F45-'4) Financial Statements'!F26))/'4) Financial Statements'!F37) -> 0.60484074
A12: Ratios de endeudamiento
A13: Endeudamiento sobre PN | B13: ='4) Financial Statements'!B52/'4) Financial Statements'!B53 -> 1.4423577 | C13: ='4) Financial Statements'!C52/'4) Financial Statements'!C53 -> 1.1390613 | D13: ='4) Financial Statements'!D52/'4) Financial Statements'!D53 -> 0.67682637 | E13: ='4) Financial Statements'!E52/'4) Financial Statements'!E53 -> 0.54762899 | F13: ='4) Financial Statements'!F52/'4) Financial Statements'!F53 -> 0.68977818
A14: Endeudamiento sobre AT | B14: ='4) Financial Statements'!B$52/'4) Financial Statements'!B$37 -> 0.59055956 | C14: ='4) Financial Statements'!C$52/'4) Financial Statements'!C$37 -> 0.53250521 | D14: ='4) Financial Statements'!D$52/'4) Financial Statements'!D$37 -> 0.40363533 | E14: ='4) Financial Statements'!E$52/'4) Financial Statements'!E$37 -> 0.35385031 | F14: ='4) Financial Statements'!F$52/'4) Financial Statements'!F$37 -> 0.40820635
A15: PT/PN | B15: ='4) Financial Statements'!B52/'4) Financial Statements'!B53 -> 1.4423577 | C15: ='4) Financial Statements'!C52/'4) Financial Statements'!C53 -> 1.1390613 | D15: ='4) Financial Statements'!D52/'4) Financial Statements'!D53 -> 0.67682637 | E15: ='4) Financial Statements'!E52/'4) Financial Statements'!E53 -> 0.54762899 | F15: ='4) Financial Statements'!F52/'4) Financial Statements'!F53 -> 0.68977818
A16: Cobertura de intereses | B16: ='4) Financial Statements'!B$16/'4) Financial Statements'!B$19 -> -1.760083 | C16: ='4) Financial Statements'!C$16/'4) Financial Statements'!C$19 -> -3.8671768 | D16: ='4) Financial Statements'!D$16/'4) Financial Statements'!D$19 -> -1.5286183 | E16: ='4) Financial Statements'!E$16/'4) Financial Statements'!E$19 -> 0.34295209 | F16: ='4) Financial Statements'!F$16/'4) Financial Statements'!F$19 -> -2.0190751
A17: Cobertura de intereses (EBITDA) | B17: =('4) Financial Statements'!B$16+'4) Financial Statements'!B$60)/'4) Financial Statements'!B$19 -> -1.8726599 | C17: =('4) Financial Statements'!C$16+'4) Financial Statements'!C$60)/'4) Financial Statements'!C$19 -> -4.0648828 | D17: =('4) Financial Statements'!D$16+'4) Financial Statements'!D$60)/'4) Financial Statements'!D$19 -> -1.7111091 | E17: =('4) Financial Statements'!E$16+'4) Financial Statements'!E$60)/'4) Financial Statements'!E$19 -> 0.1871019 | F17: =('4) Financial Statements'!F$16+'4) Financial Statements'!F$60)/'4) Financial Statements'!F$19 -> -2.534092
A18: Rotacion de credito | B18: ='4) Financial Statements'!B$7/'4) Financial Statements'!B$27 -> 10.592988 | C18: ='4) Financial Statements'!C$7/'4) Financial Statements'!C$27 -> 7.8313995 | D18: ='4) Financial Statements'!D$7/'4) Financial Statements'!D$27 -> 10.04215 | E18: ='4) Financial Statements'!E$7/'4) Financial Statements'!E$27 -> 7.0629372 | F18: ='4) Financial Statements'!F$7/'4) Financial Statements'!F$27 -> 4.9565311
A19: Dias de cobranza | B19: =('4) Financial Statements'!B$27/'4) Financial Statements'!B$7)*360 -> 33.984745 | C19: =('4) Financial Statements'!C$27/'4) Financial Statements'!C$7)*360 -> 45.968795 | D19: =('4) Financial Statements'!D$27/'4) Financial Statements'!D$7)*360 -> 35.848896 | E19: =('4) Financial Statements'!E$27/'4) Financial Statements'!E$7)*360 -> 50.970296 | F19: =('4) Financial Statements'!F$27/'4) Financial Statements'!F$7)*360 -> 72.631442
A20: Rotacion de inventario | B20: =-'4) Financial Statements'!B$8/'4) Financial Statements'!B$28 -> 5.0465431 | C20: =-'4) Financial Statements'!C$8/'4) Financial Statements'!C$28 -> 4.2166515 | D20: =-'4) Financial Statements'!D$8/'4) Financial Statements'!D$28 -> 4.5915449 | E20: =-'4) Financial Statements'!E$8/'4) Financial Statements'!E$28 -> 3.8522761 | F20: =-'4) Financial Statements'!F$8/'4) Financial Statements'!F$28 -> 5.1514426
A21: Dias de venta | B21: =('4) Financial Statements'!B$28/(-'4) Financial Statements'!B$8))*360 -> 71.335961 | C21: =('4) Financial Statements'!C$28/(-'4) Financial Statements'!C$8))*360 -> 85.375801 | D21: =('4) Financial Statements'!D$28/(-'4) Financial Statements'!D$8))*360 -> 78.404983 | E21: =('4) Financial Statements'!E$28/(-'4) Financial Statements'!E$8))*360 -> 93.451245 | F21: =('4) Financial Statements'!F$28/(-'4) Financial Statements'!F$8))*360 -> 69.883338
A22: Dias de pago | B22: =-('4) Financial Statements'!B38/'4) Financial Statements'!B8)*360 -> 60.89951 | C22: =-('4) Financial Statements'!C38/'4) Financial Statements'!C8)*360 -> 32.108895 | D22: =-('4) Financial Statements'!D38/'4) Financial Statements'!D8)*360 -> 37.933248 | E22: =-('4) Financial Statements'!E38/'4) Financial Statements'!E8)*360 -> 15.171397 | F22: =-('4) Financial Statements'!F38/'4) Financial Statements'!F8)*360 -> 43.828696
A23: Apalancamiento financiero | B23: ='4) Financial Statements'!B37/'4) Financial Statements'!B53 -> 2.4423577 | C23: ='4) Financial Statements'!C37/'4) Financial Statements'!C53 -> 2.1390613 | D23: ='4) Financial Statements'!D37/'4) Financial Statements'!D53 -> 1.6768264 | E23: ='4) Financial Statements'!E37/'4) Financial Statements'!E53 -> 1.547629 | F23: ='4) Financial Statements'!F37/'4) Financial Statements'!F53 -> 1.6897782
A24: Rotacion del activo | B24: ='4) Financial Statements'!B$7/'4) Financial Statements'!B$37 -> 1.306215 | C24: ='4) Financial Statements'!C$7/'4) Financial Statements'!C$37 -> 1.3127033 | D24: ='4) Financial Statements'!D$7/'4) Financial Statements'!D$37 -> 1.5978695 | E24: ='4) Financial Statements'!E$7/'4) Financial Statements'!E$37 -> 1.0604406 | F24: ='4) Financial Statements'!F$7/'4) Financial Statements'!F$37 -> 1.169558
A25: Ratios de rentabilidad
A26: Margen neto | B26: ='4) Financial Statements'!B22/'4) Financial Statements'!B7 -> 0.083055108 | C26: ='4) Financial Statements'!C22/'4) Financial Statements'!C7 -> 0.14118142 | D26: ='4) Financial Statements'!D22/'4) Financial Statements'!D7 -> 0.057045625 | E26: ='4) Financial Statements'!E22/'4) Financial Statements'!E7 -> -0.14405043 | F26: ='4) Financial Statements'!F22/'4) Financial Statements'!F7 -> 0.040576077
A27: ROA | B27: ='4) Financial Statements'!B22/'4) Financial Statements'!B37 -> 0.10848783 | C27: ='4) Financial Statements'!C22/'4) Financial Statements'!C37 -> 0.18532932 | D27: ='4) Financial Statements'!D22/'4) Financial Statements'!D37 -> 0.091151466 | E27: ='4) Financial Statements'!E22/'4) Financial Statements'!E37 -> -0.15275692 | F27: ='4) Financial Statements'!F22/'4) Financial Statements'!F37 -> 0.047456077
A28: ROE | B28: ='4) Financial Statements'!B22/'4) Financial Statements'!B53 -> 0.26496607 | C28: ='4) Financial Statements'!C22/'4) Financial Statements'!C53 -> 0.39643077 | D28: ='4) Financial Statements'!D22/'4) Financial Statements'!D53 -> 0.15284518 | E28: ='4) Financial Statements'!E22/'4) Financial Statements'!E53 -> -0.23641104 | F28: ='4) Financial Statements'!F22/'4) Financial Statements'!F53 -> 0.080190244
A29: ROIC | B29: ='4) Financial Statements'!B16*(1-0.35)/('4) Financial Statements'!B53+('4) Financial Statements'!B39+'4) Financial Statements'!B45-'4) Financial Statements'!B26)) -> 0.58147824 | C29: ='4) Financial Statements'!C16*(1-0.35)/('4) Financial Statements'!C53+('4) Financial Statements'!C39+'4) Financial Statements'!C45-'4) Financial Statements'!C26)) -> 0.57220375 | D29: ='4) Financial Statements'!D16*(1-0.35)/('4) Financial Statements'!D53+('4) Financial Statements'!D39+'4) Financial Statements'!D45-'4) Financial Statements'!D26)) -> 0.22087925 | E29: ='4) Financial Statements'!E16*(1-0.35)/('4) Financial Statements'!E53+('4) Financial Statements'!E39+'4) Financial Statements'!E45-'4) Financial Statements'!E26)) -> -0.06764278 | F29: ='4) Financial Statements'!F16*(1-0.35)/('4) Financial Statements'!F53+('4) Financial Statements'!F39+'4) Financial Statements'!F45-'4) Financial Statements'!F26)) -> 0.11850713
A30: Dupont | B30: =B26*B24*B23 -> 0.26496607 | C30: =C26*C24*C23 -> 0.39643077 | D30: =D26*D24*D23 -> 0.15284518 | E30: =E26*E24*E23 -> -0.23641104 | F30: =F26*F24*F23 -> 0.080190244

Sheet 6) Proyecciones
G3: =G7/F7-1 -> 0.31951456 | H3: =H7/G7-1 -> 0.11746341 | I3: =I7/H7-1 -> 0.07179236 | J3: =J7/I7-1 -> 0.051369863 | K3: =K7/J7-1 -> 0.0518591 | L3: =L7/K7-1 -> 0.0518591
A5: Variable | B5: 2020 | C5: 2021 | D5: 2022 | E5: 2023 | F5: 2024 | G5: 2025 | H5: 2026E | I5: 2027E | J5: 2028E | K5: 2029E | L5: 2030E
A6: PBI | B6: ='3) Macro'!$K7 -> -0.099 | C6: ='3) Macro'!$K8 -> 0.10441812 | D6: ='3) Macro'!$K9 -> 0.052698797 | E6: ='3) Macro'!$K10 -> -0.016110016 | F6: ='3) Macro'!$K11 -> -0.017191052 | G6: ='3) Macro'!$K12 -> 0.055 | H6: ='3) Macro'!$K13 -> 0.045 | I6: ='3) Macro'!$K14 -> 0.04 | J6: ='3) Macro'!$K15 -> 0.032 | K6: ='3) Macro'!$K16 -> 0.031 | L6: ='3) Macro'!$K17 -> 0.03
A7: TC (EOP) | B7: ='3) Macro'!$J7 -> 122.63622 | C7: ='3) Macro'!$J8 -> 164.48068 | D7: ='3) Macro'!$J9 -> 250.58223 | E7: ='3) Macro'!$J10 -> 573.54615 | F7: ='3) Macro'!$J11 -> 1163.4084 | G7: =F7*(1+G8)/(1+G10) -> 1535.1344 | H7: =G7*(1+H8)/(1+H10) -> 1715.4565 | I7: =H7*(1+I8)/(1+I10) -> 1838.6132 | J7: =I7*(1+J8)/(1+J10) -> 1933.0625 | K7: =J7*(1+K8)/(1+K10) -> 2033.3094 | L7: =K7*(1+L8)/(1+L10) -> 2138.7549
A8: Inflacion (AVG) | B8: 0.42 | C8: 0.484 | D8: 0.7243 | E8: 1.3348 | F8: 2.1988 | G8: 0.3591 | H8: 0.1454 | I8: 0.0943 | J8: 0.0745 | K8: 0.075 | L8: 0.075
A9: Inflacion (EOP) | B9: ='3) Macro'!$I7 -> 0.361 | C9: ='3) Macro'!$I8 -> 0.50941634 | D9: ='3) Macro'!$I9 -> 0.94793182 | E9: ='3) Macro'!$I10 -> 2.1140764 | F9: ='3) Macro'!$I11 -> 1.1776363 | G9: ='3) Macro'!$I12 -> 0.359 | H9: ='3) Macro'!$I13 -> 0.145 | I9: ='3) Macro'!$I14 -> 0.094 | J9: ='3) Macro'!$I15 -> 0.075 | K9: ='3) Macro'!$I16 -> 0.075 | L9: ='3) Macro'!$I17 -> 0.075
A10: Inflation USA | G10: 0.03 | H10: 0.025 | I10: 0.021 | J10: 0.022 | K10: 0.022 | L10: 0.022
A11: Precios de la industria | F11: ='2) Research'!O22 -> 112183500 | G11: =F11*(1+G8) -> 1.5246859e+08 | H11: =G11*(1+H8) -> 1.7463753e+08 | I11: =H11*(1+I8) -> 1.9110585e+08 | J11: =I11*(1+J8) -> 2.0534323e+08 | K11: =J11*(1+K8) -> 2.2074398e+08 | L11: =K11*(1+L8) -> 2.3729977e+08
A13: Revenue Model | G13: =G14/F14-1 -> 0.33765789 | H13: =H14/G14-1 -> 0.13003488 | I13: =I14/H14-1 -> 0.082510284 | J13: =J14/I14-1 -> 0.059780822 | K13: =K14/J14-1 -> 0.060011008 | L13: =L14/K14-1 -> 0.059748043 | M13: =AVERAGE(G13:L13) -> 0.12162382 | O13: Revenue | P13: =M13 -> 0.12162382
A14: Revenues | B14: =B15*B16 -> 3640221476 | C14: =C15*C16 -> 7933240381 | D14: =D15*D16 -> 14658891753 | E14: =E15*E16 -> 22474661058 | F14: =F15*F16 -> 63697863191 | G14: =G15*G16 -> 8.5205949e+10 | H14: =H15*H16 -> 9.6285694e+10 | I14: =I15*I16 -> 1.0423025e+11 | ... L14: =L15*L16 -> 1.2408602e+11 | O14: Costos operativos | P14: =M17 -> 0.10221334
A15: Price | B15: ='4) Financial Statements'!B7/'6) Proyecciones'!$B16 -> 9239140.8 | C15: ='4) Financial Statements'!C7/'6) Proyecciones'!$C16 -> 16527584 | D15: ='4) Financial Statements'!D7/'6) Proyecciones'!$D16 -> 30038713 | E15: ='4) Financial Statements'!E7/'6) Proyecciones'!$E16 -> 96873539 | F15: ='4) Financial Statements'!$F7/'6) Proyecciones'!$F16 -> 1.9967982e+08 | G15: =F15*(1+G3) -> 2.6348043e+08 | H15: =G15*(1+H3) -> 2.9442974e+08 | I15: =H15*(1+I3) -> 3.1556755e+08 | J15: =I15*(1+J3) -> 3.3177821e+08 | K15: =J15*(1+K3) -> 3.4898393e+08 | L15: =K15*(1+L3) -> 3.6708192e+08 | O15: Gastos adm | P15: =M24 -> 0.05
A16: Q (Cantidad) | B16: 394 | C16: 480 | D16: 488 | E16: 232 | F16: 319 | G16: =F16*(1+G6*$M$16) -> 323.38625 | H16: =G16*(1+H6*$M$16) -> 327.02435 | I16: =H16*(1+I6*$M$16) -> 330.29459 | J16: =I16*(1+J6*$M$16) -> 332.93695 | K16: =J16*(1+K6*$M$16) -> 335.51721 | L16: =K16*(1+L6*$M$16) -> 338.03359 | M16: =1/4 -> 0.25 | O16: Depreciaciones | P16: =M31 -> 0.047210614
G17: =G18/F18-1 -> 0.22119502 | H17: =H18/G18-1 -> 0.13003488 | I17: =I18/H18-1 -> 0.082510284 | J17: =J18/I18-1 -> 0.059780822 | K17: =K18/J18-1 -> 0.060011008 | L17: =L18/K18-1 -> 0.059748043 | M17: =AVERAGE(G17:L17) -> 0.10221334 | O17: Capex | P17: =M38 -> 0.14720254
A18: COGs | B18: ='4) Financial Statements'!B8 -> -2236831045 | C18: ='4) Financial Statements'!C8 -> -4721883737 | D18: ='4) Financial Statements'!D8 -> -8678223967 | E18: ='4) Financial Statements'!E8 -> -15735402981 | F18: ='4) Financial Statements'!F8 -> -44705660747 | G18: =-G14*G21 -> -5.459433e+10 | H18: =-H14*H21 -> -6.1693498e+10 | I18: =-I14*I21 -> -6.6783846e+10 | J18: =-J14*J21 -> -7.0776239e+10 | K18: =-K14*K21 -> -7.5023592e+10 | L18: =-L14*L21 -> -7.9506105e+10 | M18: 1.05 | O18: Delta WC | P18: =M41 -> 0.12
A19: Compras | B19: 1668743774 | C19: 3897388878 | D19: 5817495144 | E19: 7536654745 | F19: 31332654679 | G19: =-G18*G22 -> 3.7360009e+10 | H19: =-H18*H22 -> 4.1456692e+10 | I19: =-I18*I22 -> 4.282823e+10 | J19: =-J18*J22 -> 4.4977196e+10 | K19: =-K18*K22 -> 5.0024902e+10 | L19: =-L18*L22 -> 5.2471934e+10
A20: Gastos de producción | B20: 568087271 | C20: 824494859 | D20: 2860728823 | E20: 8198748236 | F20: 13373006068 | G20: =-G23*G18 -> 1.7234321e+10 | H20: =-H23*H18 -> 2.0236806e+10 | I20: =-I23*I18 -> 2.3955616e+10 | J20: =-J23*J18 -> 2.5799043e+10 | K20: =-K23*K18 -> 2.499869e+10 | L20: =-L23*L18 -> 2.7034171e+10
A21: % sobre ventas | B21: =-B18/B14 -> 0.61447664 | C21: =-C18/C14 -> 0.5952024 | D21: =-D18/D14 -> 0.59201092 | E21: =-E18/E14 -> 0.70013972 | F21: =-F18/F14 -> 0.70183925 | G21: =AVERAGE(B21:F21) -> 0.64073379 | H21: =G21 -> 0.64073379 | I21: =H21 -> 0.64073379 | J21: =I21 -> 0.64073379 | K21: =J21 -> 0.64073379 | L21: =K21 -> 0.64073379
A22: % sobre COGs | B22: =-B19/B18 -> 0.74603032 | C22: =-C19/C18 -> 0.82538857 | D22: =-D19/D18 -> 0.6703555 | E22: =-E19/E18 -> 0.47896166 | F22: =-F19/F18 -> 0.70086549 | G22: =AVERAGE(B22:F22) -> 0.68432031 | H22: =AVERAGE(C22:G22) -> 0.6719783 | I22: =AVERAGE(D22:H22) -> 0.64129625 | J22: =AVERAGE(E22:I22) -> 0.6354844 | K22: =AVERAGE(F22:J22) -> 0.66678895 | L22: =AVERAGE(G22:K22) -> 0.65997364
A23: % sobre COGs | B23: =-B20/B18 -> 0.25396968 | C23: =-C20/C18 -> 0.17461143 | D23: =-D20/D18 -> 0.3296445 | E23: =-E20/E18 -> 0.52103834 | F23: =-F20/F18 -> 0.29913451 | G23: =AVERAGE(B23:F23) -> 0.31567969 | H23: =AVERAGE(C23:G23) -> 0.3280217 | I23: =AVERAGE(D23:H23) -> 0.35870375 | J23: =AVERAGE(E23:I23) -> 0.3645156 | K23: =AVERAGE(F23:J23) -> 0.33321105 | L23: =AVERAGE(G23:K23) -> 0.34002636
G24: =G25/F25-1 -> 0.05 | H24: =H25/G25-1 -> 0.05 | I24: =I25/H25-1 -> 0.05 | J24: =J25/I25-1 -> 0.05 | K24: =K25/J25-1 -> 0.05 | L24: =L25/K25-1 -> 0.05 | M24: =AVERAGE(G24:L24) -> 0.05
A25: SG&A | B25: ='4) Financial Statements'!$B10 -> -386635412 | C25: ='4) Financial Statements'!$C10 -> -754386815 | D25: ='4) Financial Statements'!$D10 -> -1621608974 | E25: ='4) Financial Statements'!$E10 -> -4189118364 | F25: ='4) Financial Statements'!$F10 -> -9936762045 | G25: =F25*$M$25 -> -1.04336e+10 | H25: =G25*$M$25 -> -1.095528e+10 | I25: =H25*$M$25 -> -1.1503044e+10 | J25: =I25*$M$25 -> -1.2078196e+10 | K25: =J25*$M$25 -> -1.2682106e+10 | L25: =K25*$M$25 -> -1.3316211e+10 | M25: 1.05
A26: Gastos de comercialización | B26: ='4) Financial Statements'!$B11 -> 183116829 | C26: ='4) Financial Statements'!$C11 -> 358109025 | D26: ='4) Financial Statements'!$D11 -> 796614304 | E26: ='4) Financial Statements'!$E11 -> 1824457306 | F26: ='4) Financial Statements'!$F11 -> 4852573989 | G26: =-G29*G25 -> 5.5017703e+09 | H26: =-H29*H25 -> 5.7788943e+09 | I26: =-I29*I25 -> 6.0729019e+09 | J26: =-J29*J25 -> 6.4228983e+09 | K26: =-K29*K25 -> 6.6611003e+09 | L26: =-L29*L25 -> 7.0303268e+09
A27: Gastos de administración | B27: ='4) Financial Statements'!$B12 -> 203518583 | C27: ='4) Financial Statements'!$C12 -> 396277790 | D27: ='4) Financial Statements'!$D12 -> 824994670 | E27: ='4) Financial Statements'!$E12 -> 2364661058 | F27: ='4) Financial Statements'!$F12 -> 5084188056 | G27: =-G30*G25 -> 4.9318299e+09 | H27: =-H30*H25 -> 5.1763858e+09 | I27: =-I30*I25 -> 5.4301422e+09 | J27: =-J30*J25 -> 5.6552981e+09 | K27: =-K30*K25 -> 6.0210058e+09 | L27: =-L30*L25 -> 6.2858847e+09
A28: % sobre Rev. | B28: =-B25/B14 -> 0.10621206 | C28: =-C25/C14 -> 0.095091889 | D28: =-D25/D14 -> 0.11062289 | E28: =-E25/E14 -> 0.18639295 | F28: =-F25/F14 -> 0.15599836 | G28: =F28*$M$25 -> 0.16379828 | H28: =G28*(1.05) -> 0.17198819 | I28: =H28*(1.05) -> 0.1805876 | J28: =I28 -> 0.1805876 | K28: =J28 -> 0.1805876 | L28: =K28 -> 0.1805876
A29: % sobre SG&A | B29: =-B27/B25 -> 0.52638371 | C29: =-C27/C25 -> 0.52529787 | D29: =-D27/D25 -> 0.50875068 | E29: =-E27/E25 -> 0.56447702 | F29: =-F27/F25 -> 0.5116544 | G29: =AVERAGE(B29:F29) -> 0.52731274 | H29: =AVERAGE(C29:G29) -> 0.52749854 | I29: =AVERAGE(D29:H29) -> 0.52793868 | J29: =AVERAGE(E29:I29) -> 0.53177628 | K29: =AVERAGE(F29:J29) -> 0.52523613 | L29: =AVERAGE(G29:K29) -> 0.52795247
A30: % sobre SG&A | B30: =1-B29 -> 0.47361629 | C30: =1-C29 -> 0.47470213 | D30: =1-D29 -> 0.49124932 | E30: =1-E29 -> 0.43552298 | F30: =1-F29 -> 0.4883456 | G30: =AVERAGE(B30:F30) -> 0.47268726 | H30: =AVERAGE(C30:G30) -> 0.47250146 | I30: =AVERAGE(D30:H30) -> 0.47206132 | J30: =AVERAGE(E30:I30) -> 0.46822372 | K30: =AVERAGE(F30:J30) -> 0.47476387 | L30: =AVERAGE(G30:K30) -> 0.47204753
G31: =G32/F32-1 -> 0.031265307 | H31: =H32/G32-1 -> 0.0406449 | I31: =I32/H32-1 -> 0.05283837 | J31: =J32/I32-1 -> 0.05283837 | K31: =K32/J32-1 -> 0.05283837 | L31: =L32/K32-1 -> 0.05283837 | M31: =AVERAGE(G31:L31) -> 0.047210614
A32: D&A | B32: ='4) Financial Statements'!B60 -> 53264938 | C32: ='4) Financial Statements'!C60 -> 99225981 | D32: ='4) Financial Statements'!D60 -> 222987557 | E32: ='4) Financial Statements'!E60 -> 745065494 | F32: ='4) Financial Statements'!F60 -> 1531948674 | G32: =F32*(1+G35) -> 1.5798455e+09 | H32: =G32*(1+H35) -> 1.6440582e+09 | I32: =H32*(1+I35) -> 1.7309275e+09 | J32: =I32*(1+J35) -> 1.8223869e+09 | K32: =J32*(1+K35) -> 1.9186789e+09 | L32: =K32*(1+L35) -> 2.0200587e+09 | M32: 1.3
A33: ='4) Financial Statements'!A61 -> Depreciación de propiedades, planta y equipo | B33: ='4) Financial Statements'!B61 -> 53076099 | C33: ='4) Financial Statements'!C61 -> 98941022 | D33: ='4) Financial Statements'!D61 -> 222432457 | E33: ='4) Financial Statements'!E61 -> 743336913 | F33: ='4) Financial Statements'!F61 -> 1528183825 | G33: =G32*G36 -> 1.5755218e+09 | H33: =H32*H36 -> 1.6398245e+09 | I33: =I32*I36 -> 1.7265729e+09 | J33: =J32*J36 -> 1.8177926e+09 | K33: =K32*K36 -> 1.9137646e+09 | L33: =L32*L36 -> 2.0148429e+09
A34: ='4) Financial Statements'!A62 -> Depreciación de propiedades de inversión | B34: ='4) Financial Statements'!B62 -> 188839 | C34: ='4) Financial Statements'!C62 -> 284959 | D34: ='4) Financial Statements'!D62 -> 555100 | E34: ='4) Financial Statements'!E62 -> 1728581 | F34: ='4) Financial Statements'!F62 -> 3764849 | G34: =G32*G37 -> 4323742.5 | H34: =H32*H37 -> 4233648.1 | I34: =I32*I37 -> 4354634.7 | J34: =J32*J37 -> 4594350.3 | K34: =K32*K37 -> 4914248 | L34: =L32*L37 -> 5215809.3
A35: % de vtas | B35: =B32/B14 -> 0.014632334 | C35: =C32/C14 -> 0.012507623 | D35: =D32/D14 -> 0.015211761 | E35: =E32/E14 -> 0.033151356 | F35: =F32/F14 -> 0.024050236 | G35: =F35*$M$32 -> 0.031265307 | H35: =G35*$M$32 -> 0.0406449 | I35: =H35*$M$32 -> 0.05283837 | J35: =I35 -> 0.05283837 | K35: =J35 -> 0.05283837 | L35: =K35 -> 0.05283837
A36: % sobre D&A | B36: =B33/B32 -> 0.99645472 | C36: =C33/C32 -> 0.99712818 | D36: =D33/D32 -> 0.99751062 | E36: =E33/E32 -> 0.99767996 | F36: =F33/F32 -> 0.99754244 | G36: =AVERAGE(B36:F36) -> 0.99726319 | H36: =AVERAGE(C36:G36) -> 0.99742488 | I36: =AVERAGE(D36:H36) -> 0.99748422 | J36: =AVERAGE(E36:I36) -> 0.99747894 | K36: =AVERAGE(F36:J36) -> 0.99743873 | L36: =AVERAGE(G36:K36) -> 0.99741799
A37: % sobre D&A | B37: =B34/B32 -> 0.0035452778 | C37: =C34/C32 -> 0.0028718184 | D37: =D34/D32 -> 0.0024893766 | E37: =E34/E32 -> 0.002320039 | F37: =F34/F32 -> 0.0024575556 | G37: =AVERAGE(B37:F37) -> 0.0027368135 | H37: =AVERAGE(C37:G37) -> 0.0025751206 | I37: =AVERAGE(D37:H37) -> 0.002515781 | J37: =AVERAGE(E37:I37) -> 0.0025210619 | K37: =AVERAGE(F37:J37) -> 0.0025612665 | L37: =AVERAGE(G37:K37) -> 0.0025820087
G38: =G39/F39-1 -> 0.41791736 | H38: =H39/G39-1 -> 0.19783697 | I38: =I39/H39-1 -> 0.1474609 | J38: =J39/I39-1 -> 0.04 | K38: =K39/J39-1 -> 0.04 | L38: =L39/K39-1 -> 0.04 | M38: =AVERAGE(G38:L38) -> 0.14720254
A39: CAPEX | B39: ='4) Financial Statements'!B78 -> -42183587 | C39: ='4) Financial Statements'!C78 -> -158828201 | D39: ='4) Financial Statements'!D78 -> -562865660 | E39: ='4) Financial Statements'!E78 -> -811662819 | F39: ='4) Financial Statements'!F78 -> -1555724203 | G39: =-G40*G14 -> -2.2058884e+09 | H39: =-H40*H14 -> -2.6422946e+09 | I39: =-I40*I14 -> -3.0319298e+09 | J39: =I39*$N$39 -> -3.153207e+09 | K39: =J39*$N$39 -> -3.2793352e+09 | L39: =K39*$N$39 -> -3.4105087e+09 | M39: 1.06 | N39: 1.04
B40: =B39/B14*(-1) -> 0.011588192 | C40: =-C39/C14 -> 0.020020596 | D40: =-D39/D14 -> 0.038397559 | E40: =-E39/E14 -> 0.036114574 | F40: =-F39/F14 -> 0.024423491 | G40: =F40*$M$39 -> 0.025888901 | H40: =G40*$M$39 -> 0.027442235 | I40: =H40*$M$39 -> 0.029088769 | J40: =I40 -> 0.029088769 | K40: =J40 -> 0.029088769 | L40: =K40 -> 0.029088769
G41: =G42/F42-1 -> 0.12 | H41: =H42/G42-1 -> 0.12 | I41: =I42/H42-1 -> 0.12 | J41: =J42/I42-1 -> 0.12 | K41: =K42/J42-1 -> 0.12 | L41: =L42/K42-1 -> 0.12 | M41: =AVERAGE(G41:L41) -> 0.12
A42: Delta WC | C42: =C43-B43 -> 1211948904 | D42: =D43-C43 -> 1409212110 | E42: =E43-D43 -> 2324584975 | F42: =F43-E43 -> 6261283378 | G42: =F42*$M$42 -> 7.0126374e+09 | H42: =G42*$M$42 -> 7.8541539e+09 | I42: =H42*$M$42 -> 8.7966523e+09 | J42: =I42*$M$42 -> 9.8522506e+09 | K42: =J42*$M$42 -> 1.1034521e+10 | L42: =K42*$M$42 -> 1.2358663e+10 | M42: 1.12
A43: Working capital | B43: ='4) Financial Statements'!B30-'4) Financial Statements'!B44 -> 595389078 | C43: ='4) Financial Statements'!C30-'4) Financial Statements'!C44 -> 1807337982 | D43: ='4) Financial Statements'!D30-'4) Financial Statements'!D44 -> 3216550092 | E43: ='4) Financial Statements'!E30-'4) Financial Statements'!E44 -> 5541135067 | F43: ='4) Financial Statements'!F30-'4) Financial Statements'!F44 -> 11802418445 | G43: =G56*G14 -> 1.768211e+10 | H43: =H56*H14 -> 2.2379169e+10 | I43: =I56*I14 -> 2.7132762e+10 | J43: =J56*J14 -> 3.2205355e+10 | K43: =K56*K14 -> 3.8234594e+10 | L43: =L56*L14 -> 4.5381321e+10
A44: ='4) Financial Statements'!A30 -> Current Assets | B44: ='4) Financial Statements'!B30 -> 2020507012 | C44: ='4) Financial Statements'!C30 -> 4827427972 | D44: ='4) Financial Statements'!D30 -> 6465358364 | E44: ='4) Financial Statements'!E30 -> 12172506721 | F44: ='4) Financial Statements'!F30 -> 32816444384 | G44: =G43*G57 -> 4.6156932e+10 | H44: =G44*H57 -> 1.2048689e+11 | I44: =H44*I57 -> 3.1451592e+11 | J44: =I44*J57 -> 8.210044e+11 | K44: =J44*K57 -> 2.1431291e+12 | L44: =K44*L57 -> 5.59437e+12
A45: ='4) Financial Statements'!A26 -> Cash & ST Investments | B45: ='4) Financial Statements'!B26 -> 588858045 | C45: ='4) Financial Statements'!C26 -> 1186625716 | D45: ='4) Financial Statements'!D26 -> 1275948509 | E45: ='4) Financial Statements'!E26 -> 2458458439 | F45: ='4) Financial Statements'!F26 -> 7394531088 | G45: =G59*G$44 -> 1.0725944e+10 | H45: =H59*H$44 -> 2.7998732e+10 | I45: =I59*I$44 -> 7.3087183e+10 | J45: =J59*J$44 -> 1.9078493e+11 | K45: =K59*K$44 -> 4.9802016e+11 | L45: =L59*L$44 -> 1.3000192e+12
A46: ='4) Financial Statements'!A27 -> Receivables | B46: ='4) Financial Statements'!B27 -> 343644441 | C46: ='4) Financial Statements'!C27 -> 1013004174 | D46: ='4) Financial Statements'!D27 -> 1459736354 | E46: ='4) Financial Statements'!E27 -> 3182055900 | F46: ='4) Financial Statements'!F27 -> 12851298972 | G46: =G60*G$44 -> 1.1619775e+10 | H46: =H60*H$44 -> 3.0331967e+10 | I46: =I60*I$44 -> 7.9177798e+10 | J46: =J60*J$44 -> 2.0668372e+11 | K46: =K60*K$44 -> 5.3952196e+11 | L46: =L60*L$44 -> 1.4083545e+12
A47: ='4) Financial Statements'!A28 -> Inventories | B47: ='4) Financial Statements'!B28 -> 443240255 | C47: ='4) Financial Statements'!C28 -> 1119818347 | D47: ='4) Financial Statements'!D28 -> 1890044461 | E47: ='4) Financial Statements'!E28 -> 4084702777 | F47: ='4) Financial Statements'!F28 -> 8678279963 | G47: =G61*G$44 -> 1.2404139e+10 | H47: =H61*H$44 -> 3.2379451e+10 | I47: =I61*I$44 -> 8.4522499e+10 | J47: =J61*J$44 -> 2.2063539e+11 | K47: =K61*K$44 -> 5.7594104e+11 | L47: =L61*L$44 -> 1.5034219e+12
A48: ='4) Financial Statements'!A29 -> Other receivables | B48: ='4) Financial Statements'!B29 -> 644764271 | C48: ='4) Financial Statements'!C29 -> 1507979735 | D48: ='4) Financial Statements'!D29 -> 1839629040 | E48: ='4) Financial Statements'!E29 -> 2447289605 | F48: ='4) Financial Statements'!F29 -> 3892334361 | G48: =G62*G$44 -> 1.1407074e+10 | H48: =H62*H$44 -> 2.9776738e+10 | I48: =I62*I$44 -> 7.7728442e+10 | J48: =J62*J$44 -> 2.0290036e+11 | K48: =K62*K$44 -> 5.2964596e+11 | L48: =L62*L$44 -> 1.3825744e+12
A49: ='4) Financial Statements'!A44 -> Current Liabilities | B49: ='4) Financial Statements'!B44 -> 1425117934 | C49: ='4) Financial Statements'!C44 -> 3020089990 | D49: ='4) Financial Statements'!D44 -> 3248808272 | E49: ='4) Financial Statements'!E44 -> 6631371654 | F49: ='4) Financial Statements'!F44 -> 21014025939 | G49: =G58*G43 -> 2.8474822e+10 | H49: =H58*H43 -> 3.6038847e+10 | I49: =I58*I43 -> 4.3693914e+10 | J49: =J58*J43 -> 5.1862688e+10 | K49: =K58*K43 -> 6.1572023e+10 | L49: =L58*L43 -> 7.3080931e+10
A50: ='4) Financial Statements'!A38 -> Payables | B50: ='4) Financial Statements'!B38 -> 378394206 | C50: ='4) Financial Statements'!C38 -> 421151305 | D50: ='4) Financial Statements'!D38 -> 914425611 | E50: ='4) Financial Statements'!E38 -> 663133450 | F50: ='4) Financial Statements'!F38 -> 5442752288 | G50: =G$49*G63 -> 5.9537311e+09 | H50: =H$49*H63 -> 7.1285384e+09 | I50: =I$49*I63 -> 9.1526439e+09 | J50: =J$49*J63 -> 1.0117021e+10 | K50: =K$49*K63 -> 1.3181829e+10 | L50: =L$49*L63 -> 1.4989221e+10
A51: ='4) Financial Statements'!A39 -> Loans | B51: ='4) Financial Statements'!B39 -> 293554093 | C51: ='4) Financial Statements'!C39 -> 482245050 | D51: ='4) Financial Statements'!D39 -> 1031754217 | E51: ='4) Financial Statements'!E39 -> 3665556676 | F51: ='4) Financial Statements'!F39 -> 6886952651 | G51: =G$49*G64 -> 8.9054171e+09 | H51: =H$49*H64 -> 1.2040554e+10 | I51: =I$49*I64 -> 1.6122328e+10 | J51: =J$49*J64 -> 1.966966e+10 | K51: =K$49*K64 -> 2.1215566e+10 | L51: =L$49*L64 -> 2.5427179e+10
A52: ='4) Financial Statements'!A40 -> Remuneraciones y Deudas sociales | B52: ='4) Financial Statements'!B40 -> 74744081 | C52: ='4) Financial Statements'!C40 -> 179220183 | D52: ='4) Financial Statements'!D40 -> 296617720 | E52: ='4) Financial Statements'!E40 -> 581546869 | F52: ='4) Financial Statements'!F40 -> 1280599720 | G52: =G$49*G65 -> 2.0030747e+09 | H52: =H$49*H65 -> 2.6641729e+09 | I52: =I$49*I65 -> 3.357506e+09 | J52: =J$49*J65 -> 3.8352308e+09 | K52: =K$49*K65 -> 4.383952e+09 | L52: =L$49*L65 -> 5.3533551e+09
A53: ='4) Financial Statements'!A41 -> Fiscales | B53: ='4) Financial Statements'!B41 -> 127303502 | C53: ='4) Financial Statements'!C41 -> 635763012 | D53: ='4) Financial Statements'!D41 -> 113803295 | E53: ='4) Financial Statements'!E41 -> 88779717 | F53: ='4) Financial Statements'!F41 -> 2924936225 | G53: =G$49*G66 -> 2.7759903e+09 | H53: =H$49*H66 -> 3.5722237e+09 | I53: =I$49*I66 -> 3.3575938e+09 | J53: =J$49*J66 -> 4.4190312e+09 | K53: =K$49*K66 -> 6.1307307e+09 | L53: =L$49*L66 -> 6.6975854e+09
A54: ='4) Financial Statements'!A42 -> Anticipos de Clientes | B54: ='4) Financial Statements'!B42 -> 514650909 | C54: ='4) Financial Statements'!C42 -> 1204710440 | D54: ='4) Financial Statements'!D42 -> 675522485 | E54: ='4) Financial Statements'!E42 -> 950830550 | F54: ='4) Financial Statements'!F42 -> 3092212223 | G54: =G$49*G67 -> 7.1670583e+09 | H54: =H$49*H67 -> 8.2821587e+09 | I54: =I$49*I67 -> 8.563771e+09 | J54: =J$49*J67 -> 1.0041013e+10 | K54: =K$49*K67 -> 1.2539293e+10 | L54: =L$49*L67 -> 1.5708962e+10
A55: ='4) Financial Statements'!A43 -> Other | B55: ='4) Financial Statements'!B43 -> 36471143 | C55: ='4) Financial Statements'!C43 -> 97000000 | D55: ='4) Financial Statements'!D43 -> 216684944 | E55: ='4) Financial Statements'!E43 -> 681524392 | F55: ='4) Financial Statements'!F43 -> 1386572832 | G55: =G$49*G68 -> 1.6695508e+09 | H55: =H$49*H68 -> 2.3511996e+09 | I55: =I$49*I68 -> 3.1400714e+09 | J55: =J$49*J68 -> 3.7807317e+09 | K55: =K$49*K68 -> 4.1206522e+09 | L55: =L$49*L68 -> 4.9046277e+09
A56: % del Rev | B56: =B43/B14 -> 0.16355848 | C56: =C43/C14 -> 0.22781838 | D56: =D43/D14 -> 0.21942655 | E56: =E43/E14 -> 0.24655033 | F56: =F43/F14 -> 0.18528751 | G56: =F56*$M$42 -> 0.20752201 | H56: =G56*$M$42 -> 0.23242465 | I56: =H56*$M$42 -> 0.26031561 | J56: =I56*$M$42 -> 0.29155348 | K56: =J56*$M$42 -> 0.3265399 | L56: =K56*$M$42 -> 0.36572469
A57: % del WC | B57: =B44/B43 -> 3.393591 | C57: =C44/C43 -> 2.6710156 | D57: =D44/D43 -> 2.0100288 | E57: =E44/E43 -> 2.1967533 | F57: =F44/F43 -> 2.7804847 | G57: =AVERAGE(B57:F57) -> 2.6103747 | H57: =G57 -> 2.6103747 | I57: =H57 -> 2.6103747 | J57: =I57 -> 2.6103747 | K57: =J57 -> 2.6103747 | L57: =K57 -> 2.6103747
A58: % del WC | B58: =B49/B43 -> 2.393591 | C58: =C49/C43 -> 1.6710156 | D58: =D49/D43 -> 1.0100288 | E58: =E49/E43 -> 1.1967533 | F58: =F49/F43 -> 1.7804847 | G58: =AVERAGE(B58:F58) -> 1.6103747 | H58: =G58 -> 1.6103747 | I58: =H58 -> 1.6103747 | J58: =I58 -> 1.6103747 | K58: =J58 -> 1.6103747 | L58: =K58 -> 1.6103747
A59: Cash & ST Investments | B59: =B45/B$44 -> 0.29144073 | C59: =C45/C$44 -> 0.2458091 | D59: =D45/D$44 -> 0.19735155 | E59: =E45/E$44 -> 0.20196813 | F59: =F45/F$44 -> 0.22533005 | G59: =AVERAGE(B59:F59) -> 0.23237991 | H59: =G59 -> 0.23237991 | I59: =H59 -> 0.23237991 | J59: =I59 -> 0.23237991 | K59: =J59 -> 0.23237991 | L59: =K59 -> 0.23237991
A60: Receivables | B60: =B46/B$44 -> 0.17007832 | C60: =C46/C$44 -> 0.20984346 | D60: =D46/D$44 -> 0.2257781 | E60: =E46/E$44 -> 0.26141336 | F60: =F46/F$44 -> 0.39161156 | G60: =AVERAGE(B60:F60) -> 0.25174496 | H60: =G60 -> 0.25174496 | I60: =H60 -> 0.25174496 | J60: =I60 -> 0.25174496 | K60: =J60 -> 0.25174496 | L60: =K60 -> 0.25174496
A61: Inventories | B61: =B47/B$44 -> 0.21937081 | C61: =C47/C$44 -> 0.23196998 | D61: =D47/D$44 -> 0.29233406 | E61: =E47/E$44 -> 0.33556792 | F61: =F47/F$44 -> 0.26444912 | G61: =AVERAGE(B61:F61) -> 0.26873838 | H61: =G61 -> 0.26873838 | I61: =H61 -> 0.26873838 | J61: =I61 -> 0.26873838 | K61: =J61 -> 0.26873838 | L61: =K61 -> 0.26873838
A62: Other receivables | B62: =B48/B$44 -> 0.31911014 | C62: =C48/C$44 -> 0.31237747 | D62: =D48/D$44 -> 0.28453628 | E62: =E48/E$44 -> 0.20105059 | F62: =F48/F$44 -> 0.11860927 | G62: =AVERAGE(B62:F62) -> 0.24713675 | H62: =G62 -> 0.24713675 | I62: =H62 -> 0.24713675 | J62: =I62 -> 0.24713675 | K62: =J62 -> 0.24713675 | L62: =K62 -> 0.24713675
A63: Payables | B63: =B50/B$49 -> 0.26551782 | C63: =C50/C$49 -> 0.13944992 | D63: =D50/D$49 -> 0.28146494 | E63: =E50/E$49 -> 0.09999944 | F63: =F50/F$49 -> 0.25900569 | G63: =AVERAGE(B63:F63) -> 0.20908756 | H63: =AVERAGE(C63:G63) -> 0.19780151 | I63: =AVERAGE(D63:H63) -> 0.20947183 | J63: =AVERAGE(E63:I63) -> 0.19507321 | K63: =AVERAGE(F63:J63) -> 0.21408796 | L63: =AVERAGE(G63:K63) -> 0.20510441
A64: Loans | B64: =B51/B$49 -> 0.20598582 | C64: =C51/C$49 -> 0.15967903 | D64: =D51/D$49 -> 0.31757929 | E64: =E51/E$49 -> 0.55275995 | F64: =F51/F$49 -> 0.32773123 | G64: =AVERAGE(B64:F64) -> 0.31274707 | H64: =AVERAGE(C64:G64) -> 0.33409931 | I64: =AVERAGE(D64:H64) -> 0.36898337 | J64: =AVERAGE(E64:I64) -> 0.37926419 | K64: =AVERAGE(F64:J64) -> 0.34456503 | L64: =AVERAGE(G64:K64) -> 0.34793179
A65: Remuneraciones y Deudas sociales | B65: =B52/B$49 -> 0.052447646 | C65: =C52/C$49 -> 0.059342663 | D65: =D52/D$49 -> 0.091300469 | E65: =E52/E$49 -> 0.087696317 | F65: =F52/F$49 -> 0.060940237 | G65: =AVERAGE(B65:F65) -> 0.070345466 | H65: =AVERAGE(C65:G65) -> 0.073925031 | I65: =AVERAGE(D65:H65) -> 0.076841504 | J65: =AVERAGE(E65:I65) -> 0.073949711 | K65: =AVERAGE(F65:J65) -> 0.07120039 | L65: =AVERAGE(G65:K65) -> 0.07325242
A66: Fiscales | B66: =B53/B$49 -> 0.089328398 | C66: =C53/C$49 -> 0.21051128 | D66: =D53/D$49 -> 0.035029243 | E66: =E53/E$49 -> 0.013387836 | F66: =F53/F$49 -> 0.13918971 | G66: =AVERAGE(B66:F66) -> 0.097489294 | H66: =AVERAGE(C66:G66) -> 0.099121473 | I66: =AVERAGE(D66:H66) -> 0.076843512 | J66: =AVERAGE(E66:I66) -> 0.085206366 | K66: =AVERAGE(F66:J66) -> 0.099570071 | L66: =AVERAGE(G66:K66) -> 0.091646143
A67: Anticipos de Clientes | B67: =B54/B$49 -> 0.36112865 | C67: =C54/C$49 -> 0.39889886 | D67: =D54/D$49 -> 0.20792932 | E67: =E54/E$49 -> 0.14338369 | F67: =F54/F$49 -> 0.14714992 | G67: =AVERAGE(B67:F67) -> 0.25169809 | H67: =AVERAGE(C67:G67) -> 0.22981197 | I67: =AVERAGE(D67:H67) -> 0.1959946 | J67: =AVERAGE(E67:I67) -> 0.19360765 | K67: =AVERAGE(F67:J67) -> 0.20365245 | L67: =AVERAGE(G67:K67) -> 0.21495295
A68: Other | B68: =B55/B$49 -> 0.025591667 | C68: =C55/C$49 -> 0.032118248 | D68: =D55/D$49 -> 0.066696747 | E68: =E55/E$49 -> 0.10277276 | F68: =F55/F$49 -> 0.065983207 | G68: =AVERAGE(B68:F68) -> 0.058632527 | H68: =AVERAGE(C68:G68) -> 0.065240699 | I68: =AVERAGE(D68:H68) -> 0.071865189 | J68: =AVERAGE(E68:I68) -> 0.072898877 | K68: =AVERAGE(F68:J68) -> 0.0669241 | L68: =AVERAGE(G68:K68) -> 0.067112278
A71: Loans current | B71: ='4) Financial Statements'!B39 -> 293554093 | C71: ='4) Financial Statements'!C39 -> 482245050 | D71: ='4) Financial Statements'!D39 -> 1031754217 | E71: ='4) Financial Statements'!E39 -> 3665556676 | F71: ='4) Financial Statements'!F39 -> 6886952651 | G71: =G51 -> 8.9054171e+09
A72: Loans no current | B72: ='4) Financial Statements'!B45 -> 85161167 | C72: ='4) Financial Statements'!C45 -> 83869806 | D72: ='4) Financial Statements'!D45 -> 269771457 | E72: ='4) Financial Statements'!E45 -> 853382678 | F72: ='4) Financial Statements'!F45 -> 1218164492 | G72: =F72*G73 -> 1.4594204e+09
C73: =C72/B72-1 -> -0.015163731 | D73: =D72/C72-1 -> 2.2165504 | E73: =E72/D72-1 -> 2.1633542 | F73: =F72/E72-1 -> 0.42745397 | G73: =AVERAGE(C73:F73) -> 1.1980487
A74: % | C74: =C71/B71-1 -> 0.64278088 | D74: =D71/C71-1 -> 1.1394812 | E74: =E71/D71-1 -> 2.5527421 | F74: =F71/E71-1 -> 0.87882858 | G74: =AVERAGE(C74:F74) -> 1.3034582
A75: Cash | B75: ='4) Financial Statements'!B26 -> 588858045 | C75: ='4) Financial Statements'!C26 -> 1186625716 | D75: ='4) Financial Statements'!D26 -> 1275948509 | E75: ='4) Financial Statements'!E26 -> 2458458439 | F75: ='4) Financial Statements'!F26 -> 7394531088 | G75: =F75*G76 -> 7.4406842e+09
C76: =C75/B75-1 -> 1.0151303 | D76: =D75/C75-1 -> 0.075274614 | E76: =E75/D75-1 -> 0.92676932 | F76: =F75/E75-1 -> 2.0077918 | G76: =AVERAGE(C76:F76) -> 1.0062415
G79: =G72+G71 -> 1.0364838e+10 | H79: =G79/G7 -> 6751746.1
G80: =G75 -> 7.4406842e+09 | H80: =G80/G7 -> 4846927

Sheet FCFF
C1: 2026E | D1: 2027E | E1: 2028E | F1: 2029E | G1: 2030E
B2: Dólar promedio | C2: ='6) Proyecciones'!H$7 -> 1715.4565 | D2: ='6) Proyecciones'!I$7 -> 1838.6132 | E2: ='6) Proyecciones'!J$7 -> 1933.0625 | F2: ='6) Proyecciones'!K$7 -> 2033.3094 | G2: ='6) Proyecciones'!L$7 -> 2138.7549
B3: Delta Working Capital | C3: ='6) Proyecciones'!H42 -> 7.8541539e+09 | D3: ='6) Proyecciones'!I42 -> 8.7966523e+09 | E3: ='6) Proyecciones'!J42 -> 9.8522506e+09 | F3: ='6) Proyecciones'!K42 -> 1.1034521e+10 | G3: ='6) Proyecciones'!L42 -> 1.2358663e+10
I5: Risk Free | J5: 0.04 | K5: WACC
I6: Country Risk (EMBI+) | J6: =J5+0.005 -> 0.045 | M6: 1,5; 2%
I7: Rm | J7: 0.08 | M7: 6 y/o 8% MERVAL
B8: $ | I8: Beta | J8: ='1) Estadística'!P53 -> 0.87767651
B9: Revenues | C9: ='6) Proyecciones'!H14 -> 9.6285694e+10 | D9: ='6) Proyecciones'!I14 -> 1.0423025e+11 | E9: ='6) Proyecciones'!J14 -> 1.1046122e+11 | F9: ='6) Proyecciones'!K14 -> 1.1709011e+11 | G9: ='6) Proyecciones'!L14 -> 1.2408602e+11 | I9: Ke | J9: =J5+J6+(J8*(J7-J5)) -> 0.12010706
B10: Operating Costs | C10: ='6) Proyecciones'!H18 -> -6.1693498e+10 | D10: ='6) Proyecciones'!I18 -> -6.6783846e+10 | E10: ='6) Proyecciones'!J18 -> -7.0776239e+10 | F10: ='6) Proyecciones'!K18 -> -7.5023592e+10 | G10: ='6) Proyecciones'!L18 -> -7.9506105e+10 | I10: Kd (Cost of Capital) | J10: 0.09
B11: Gross Income | C11: =C9+C10 -> 3.4592197e+10 | D11: =D9+D10 -> 3.7446409e+10 | E11: =E9+E10 -> 3.9684986e+10 | F11: =F9+F10 -> 4.2066522e+10 | G11: =G9+G10 -> 4.4579914e+10 | I11: Tax Rate | J11: =-'4) Financial Statements'!G24 -> 0.35494429
B12: SG&A | C12: ='6) Proyecciones'!H25 -> -1.095528e+10 | D12: ='6) Proyecciones'!I25 -> -1.1503044e+10 | E12: ='6) Proyecciones'!J25 -> -1.2078196e+10 | F12: ='6) Proyecciones'!K25 -> -1.2682106e+10 | G12: ='6) Proyecciones'!L25 -> -1.3316211e+10 | I12: E/E+D | J12: ='4) Financial Statements'!F53/('4) Financial Statements'!F53+'4) Financial Statements'!F45+'4) Financial Statements'!F39) -> 0.7990604 | M12: 70% optimo
B13: EBIT | C13: =C11+C12 -> 2.3636917e+10 | D13: =D11+D12 -> 2.5943365e+10 | E13: =E11+E12 -> 2.760679e+10 | F13: =F11+F12 -> 2.9384416e+10 | G13: =G11+G12 -> 3.1263703e+10 | I13: WACC | J13: =(J9*J12)+(J10*(1-J11)*(1-J12)) -> 0.10763835 | M13: 10,5-13
B14: Tax | C14: =-C13*$J$11 -> -8.3897886e+09 | D14: =-D13*$J$11 -> -9.2084492e+09 | E14: =-E13*$J$11 -> -9.7988723e+09 | F14: =-F13*$J$11 -> -1.0429831e+10 | G14: =-G13*$J$11 -> -1.1096873e+10 | I14: Perpetuity | J14: 0.025
B15: D&A | C15: ='6) Proyecciones'!H32 -> 1.6440582e+09 | D15: ='6) Proyecciones'!I32 -> 1.7309275e+09 | E15: ='6) Proyecciones'!J32 -> 1.8223869e+09 | F15: ='6) Proyecciones'!K32 -> 1.9186789e+09 | G15: ='6) Proyecciones'!L32 -> 2.0200587e+09
B16: Delta Working Capital | C16: =C3*-1 -> -7.8541539e+09 | D16: =D3*-1 -> -8.7966523e+09 | E16: =E3*-1 -> -9.8522506e+09 | F16: =F3*-1 -> -1.1034521e+10 | G16: =G3*-1 -> -1.2358663e+10
B17: Capex | C17: ='6) Proyecciones'!H39 -> -2.6422946e+09 | D17: ='6) Proyecciones'!I39 -> -3.0319298e+09 | E17: ='6) Proyecciones'!J39 -> -3.153207e+09 | F17: ='6) Proyecciones'!K39 -> -3.2793352e+09 | G17: ='6) Proyecciones'!L39 -> -3.4105087e+09
B18: Free Cash Flow to the Firm (FCFF) | C18: =SUM(C13:C17) -> 6.3947377e+09 | D18: =SUM(D13:D17) -> 6.6372609e+09 | E18: =SUM(E13:E17) -> 6.6248465e+09 | F18: =SUM(F13:F17) -> 6.559408e+09 | G18: =SUM(G13:G17) -> 6.4177169e+09
B21: US$
B22: Revenues | C22: =C9/C$2 -> 56128322 | D22: =D9/D$2 -> 56689605 | E22: =E9/E$2 -> 57143122 | F22: =F9/F$2 -> 57585981 | G22: =G9/G$2 -> 58017876
B23: Operating Costs | C23: =C10/C$2 -> -35963312 | D23: =D10/D$2 -> -36322945 | E23: =E10/E$2 -> -36613529 | F23: =F10/F$2 -> -36897284 | G23: =G10/G$2 -> -37174013
B24: Gross Income | C24: =C22+C23 -> 20165010 | D24: =D22+D23 -> 20366660 | E24: =E22+E23 -> 20529593 | F24: =F22+F23 -> 20688697 | G24: =G22+G23 -> 20843863
B25: SG&A | C25: =C12/C$2 -> -6386218.6 | D25: =D12/D$2 -> -6256369.9 | E25: =E12/E$2 -> -6248218.3 | F25: =F12/F$2 -> -6237175 | G25: =G12/G$2 -> -6226151.1
B26: EBIT | C26: =C24+C25 -> 13778791 | D26: =D24+D25 -> 14110290 | E26: =E24+E25 -> 14281375 | F26: =F24+F25 -> 14451522 | G26: =G24+G25 -> 14617711
B27: Tax | C27: =C14/C$2 -> -4890703.2 | D27: =D14/D$2 -> -5008366.8 | E27: =E14/E$2 -> -5069092.4 | F27: =F14/F$2 -> -5129485.4 | G27: =G14/G$2 -> -5188473.2
B28: D&A | C28: =C15/C$2 -> 958379.41 | D28: =D15/D$2 -> 941431.06 | E28: =E15/E$2 -> 942746 | F28: =F15/F$2 -> 943623.69 | G28: =G15/G$2 -> 944502.19
B29: Delta Working Capital | C29: =C16/C$2 -> -4578462.9 | D29: =D16/D$2 -> -4784395.4 | E29: =E16/E$2 -> -5096705.7 | F29: =F16/F$2 -> -5426877.4 | G29: =G16/G$2 -> -5778438.1
B30: Capex | C30: =C17/C$2 -> -1540286.6 | D30: =D17/D$2 -> -1649030.8 | E30: =E17/E$2 -> -1631197.6 | F30: =F17/F$2 -> -1612806.8 | G30: =G17/G$2 -> -1594623.4
B31: Free Cash Flow to the Firm (FCFF) | C31: =SUM(C26:C30) -> 3727717.8 | D31: =SUM(D26:D30) -> 3609927.8 | E31: =SUM(E26:E30) -> 3427124.9 | F31: =SUM(F26:F30) -> 3225976.4 | G31: =SUM(G26:G30) -> 3000678.9
B32: Discounted FCFF | C32: =C31 -> 3727717.8 | D32: =D31/(1+$J$13) -> 3259121.4 | E32: =E31/(1+$J$13)^2 -> 2793405.4 | F32: =F31/(1+$J$13)^3 -> 2373926.3 | G32: =G31/(1+$J$13)^4 -> 1993552.1
B33: VAN | C33: =SUM(C32:G32) -> 14147723
D36: 5Y VAN | E36: =C33 -> 14147723 | I36: Market Cap | J36: =E41*E43 -> 36153187 | L36: Ticker | M36: EV/EBITDA
D37: Perpetuity | E37: =(G31*(1+$J$14))/(J13-J14) -> 37218749 | I37: Debt | J37: =E38 -> 6751746.1 | L37: DE | M37: 15.83
C38: Net Debt | D38: Debt | E38: =('6) Proyecciones'!G71+'6) Proyecciones'!G72)/'6) Proyecciones'!G7 -> 6751746.1 | I38: Cash | J38: =E39 -> 4846927 | L38: AGRO | M38: =Relative_Valuation!B29 -> 1.9085614
D39: Cash | E39: ='6) Proyecciones'!G75/'6) Proyecciones'!G7 -> 4846927 | I39: EV | J39: =J36+J37-J38 -> 38058006 | L39: AGCO | M39: 11.89
D40: 2025 Equity | E40: =E36+E37-E38+E39 -> 49461653 | I40: EBITDA 2025 | J40: =('6) Proyecciones'!G14+'6) Proyecciones'!G18)/'6) Proyecciones'!G7 -> 19940677 | L40: CNHI | M40: 11.94
D41: Q Shares | E41: 1200000000 | L41: KUBTY | M41: 8.75
D42: Target Price | E42: =E40/E41 -> 0.041218044
D43: Market Price | E43: =46.25/'6) Proyecciones'!G7 -> 0.030127656
D44: Upside | E44: =(E42/E43)-1 -> 0.36811321
D46: Upside del U$S | E46: ='6) Proyecciones'!G3 -> 0.31951456
D47: Upside en $ | E47: =(1+E44*1+E46)-1 -> 0.68762777 | F47: último máximo

Sheet Relative_Valuation
A3: Año | B3: 2020 | C3: 2021 | D3: 2022 | E3: 2023 | F3: 2024 | G3: 2025E
A4: Net income | B4: ='6) Proyecciones'!B14+'6) Proyecciones'!B18 -> 1403390431 | C4: ='6) Proyecciones'!C14+'6) Proyecciones'!C18 -> 3211356644 | D4: ='6) Proyecciones'!D14+'6) Proyecciones'!D18 -> 5980667786 | E4: ='6) Proyecciones'!E14+'6) Proyecciones'!E18 -> 6739258077 | F4: ='6) Proyecciones'!F14+'6) Proyecciones'!F18 -> 18992202444 | G4: ='6) Proyecciones'!G14+'6) Proyecciones'!G18 -> 3.0611619e+10
A5: Acciones en circulación | B5: 100000000 | C5: 100000000 | D5: 100000000 | E5: =[2]FCFF!$E$41 -> 1200000000 | F5: =[2]FCFF!$E$41 -> 1200000000 | G5: =[2]FCFF!$E$41 -> 1200000000
A6: EPS | B6: =B4/B5 -> 14.033904 | C6: =C4/C5 -> 32.113566 | D6: =D4/D5 -> 59.806678 | E6: =E4/E5 -> 5.6160484 | F6: =F4/F5 -> 15.826835 | G6: =G4/G5 -> 25.509682
G7: =G6/'6) Proyecciones'!G7 -> 0.016617231
A9: Empresa | B9: Ticker | C9: P/E
A10: Deere&Company | B10: DE | C10: 5.61
A11: Agrometal | B11: AGRO.m | C11: 1.78
A12: Brasilagro | B12: LND | C12: 0.93
A13: Itausa | B13: ITSA4 | C13: 1.34
A14: Adecoagro | B14: AGRO | C14: 0.67
A15: KubotaCorp | B15: 6326 | C15: 0.77
A16: AGCO Corporation | B16: AGCO | C16: 2.12
A17: CNH Industrial NV | B17: CNHI | C17: 2.11
A18: Promedio | C18: =AVERAGE(C11:C17) -> 1.3885714
A20: P/E target | B20: 2
A21: Target price | B21: =B20*G6 -> 51.019365
A22: Target price en u$s | B22: =B21/'6) Proyecciones'!G7 -> 0.033234462
A23: Market price | B23: =FCFF!E43 -> 0.030127656
A24: Upside | B24: =B22/B23-1 -> 0.10312139
B28: 2025 | C28: 2026E | D28: 2027E | E28: 2028E | F28: 2029E | G28: 2030E
A29: EV/EBITDA | B29: =FCFF!$J$39/FCFF!J40 -> 1.9085614 | C29: =FCFF!$J$39/FCFF!C24 -> 1.8873289 | D29: =FCFF!$J$39/FCFF!D24 -> 1.8686425 | E29: =FCFF!$J$39/FCFF!E24 -> 1.853812 | F29: =FCFF!$J$39/FCFF!F24 -> 1.8395555 | G29: =FCFF!$J$39/FCFF!G24 -> 1.8258615
